Workbook

Sheet Rules
A1: 1. Data laporan Stcok Alkes

Sheet REKON AP
A2: Customer | B2: No NPWP | C2: Item | D2: PO No. | E2: Date Invoice | F2: Invoice | G2: Date | H2: No Kwitansi | I2: Nilai Inv | J2: DPP | K2: DPP LAINNYA | L2: PPN Bendaharawan | M2: PPN | N2: PPh 23 | O2: PPh 22 | P2: Payment | Q2: DO.NO | R2: Code | S2: No Faktur | V2: Date | W2: Payment | X2: Description
A3: a
A4: RUMAH SAKIT UMUM DAERAH CIBINONG KABUPATEN BOGOR | B4: 656901832403000 | E4: 19/02/2025 | I4: =J4+L4 -> 10771251 | J4: 9703830 | K4: 8895178 | L4: 1067421 | O4: =J4*1.5% -> 145557.45 | P4: =J4+M4-O4 -> 9558272.6 | S4: 2.0025e+15
A5: DINAS KESEHATAN KABUPATEN BOGOR | B5: 1368901403000 | E5: 13/03/2025 | I5: =J5+L5 -> 6065000 | J5: 5463963 | K5: 5008632 | L5: 601037 | O5: =J5*1.5% -> 81959.445 | P5: =J5+M5-O5 -> 5382003.6 | S5: 2.0025001e+15
A6: DINAS KESEHATAN KABUPATEN BOGOR | B6: 1368901403000 | E6: 21/03/2025 | I6: =J6+L6 -> 865297061 | J6: 779546902 | K6: 714584660 | L6: 85750159 | O6: =J6*1.5% -> 11693204 | P6: =J6+M6-O6 -> 7.678537e+08 | S6: 2.0025001e+15
A7: DINAS KESEHATAN KABUPATEN BOGOR | B7: 1368901403000 | E7: 26/03/2025 | I7: =J7+L7 -> 17132001 | J7: 15434239 | K7: 14148011 | L7: 1697762 | O7: =J7*1.5% -> 231513.58 | P7: =J7+M7-O7 -> 15202725 | S7: 2.0025001e+15
A8: DINAS KESEHATAN KABUPATEN BOGOR | B8: 1368901403000 | E8: 45965 | I8: =J8+L8 -> 1342500 | J8: 1209459 | K8: 1108671 | L8: 133041 | O8: =J8*1.5% -> 18141.885 | P8: =J8+M8-O8 -> 1191317.1 | S8: 2.0025001e+15
A9: DINAS KESEHATAN KABUPATEN BOGOR | B9: 1368901403000 | E9: 17/04/2025 | I9: =J9+L9 -> 7254054 | J9: 6600000 | K9: 5450450 | L9: 654054 | O9: =J9*1.5% -> 99000 | P9: =J9+M9-O9 -> 6501000 | S9: 2.0025001e+15
A10: DINAS KESEHATAN KABUPATEN BOGOR | B10: 1368901403000 | E10: 17/04/2025 | I10: 6935500 | J10: =I10/1.11 -> 6248198.2 | K10: 5727515 | L10: 687302 | O10: =J10*1.5% -> 93722.973 | P10: =J10+M10-O10 -> 6154475.2 | S10: 2.0025001e+15
A11: DINAS KESEHATAN KABUPATEN BOGOR | B11: 1368901403000 | E11: 17/04/2025 | I11: =J11+L11 -> 1017766 | J11: 926000 | K11: 764715 | L11: 91766 | O11: =J11*1.5% -> 13890 | P11: =J11+M11-O11 -> 912110 | S11: 2.0025001e+15
A12: DINAS KESEHATAN KABUPATEN BOGOR | B12: 1368901403000 | E12: 17/04/2025 | I12: =J12+L12 -> 22652432 | J12: 20610000 | K12: 17020270 | L12: 2042432 | O12: =J12*1.5% -> 309150 | P12: =J12+M12-O12 -> 20300850 | S12: 2.0025001e+15
A13: DINAS KESEHATAN KABUPATEN BOGOR | B13: 1368901403000 | E13: 21/04/2025 | I13: =J13+L13 -> 55571499 | J13: 50064414 | K13: 45892379 | L13: 5507085 | O13: =J13*1.5% -> 750966.21 | P13: =J13+M13-O13 -> 49313448 | S13: 2.0025001e+15
A14: DINAS KESEHATAN KABUPATEN BOGOR | B14: 1368901403000 | E14: 21/04/2025 | I14: =J14+L14 -> 9955250 | J14: 8968694 | K14: 8221303 | L14: 986556 | O14: =J14*1.5% -> 134530.41 | P14: =J14+M14-O14 -> 8834163.6 | S14: 2.0025001e+15
A15: DINAS KESEHATAN KABUPATEN BOGOR | B15: 1368901403000 | E15: 23/04/2025 | I15: =J15+L15 -> 24749992 | J15: 22297290 | K15: 20439183 | L15: 2452702 | O15: =J15*1.5% -> 334459.35 | P15: =J15+M15-O15 -> 21962831 | S15: 2.0025001e+15
A16: Puskesmas Gobang | B16: 1368901403000 | E16: 22/05/2025 | I16: =J16+L16 -> 10982484 | J16: 9805657 | K16: 9805657 | L16: 1176827 | O16: =J16*1.5% -> 147084.86 | P16: =J16+M16-O16 -> 9658572.1 | S16: 2.0025002e+15
A17: DINAS KESEHATAN KABUPATEN BOGOR | B17: 1368901403000 | E17: 45694 | I17: =J17+L17 -> 4924998 | J17: 4436935 | K17: 4067190 | L17: 488063 | O17: =J17*1.5% -> 66554.025 | P17: =J17+M17-O17 -> 4370381 | S17: 2.0025002e+15
A18: DINAS KESEHATAN KABUPATEN BOGOR | B18: 1368901403000 | E18: 45694 | I18: =J18+L18 -> 1648500 | J18: 1485135 | K18: 1361373 | L18: 163365 | O18: =J18*1.5% -> 22277.025 | P18: =J18+M18-O18 -> 1462858 | S18: 2.0025002e+15
A19: RUMAH SAKIT UMUM DAERAH KOTA DUMAI | B19: 1211994212000 | E19: 45967 | I19: =J19+L19 -> 62128800 | J19: 55971892 | K19: 51307567 | L19: 6156908 | O19: =J19*1.5% -> 839578.38 | P19: =J19+M19-O19 -> 55132314 | S19: 4.0025002e+15
A20: DINAS KESEHATAN KABUPATEN BOGOR | B20: 1368901403000 | E20: 45997 | I20: =J20+L20 -> 1485135 | J20: 1485135 | K20: 1361374 | M20: 163365 | O20: =J20*1.5% -> 22277.025 | P20: =J20+M20-O20 -> 1626223 | S20: 2.0025002e+15
A21: DINAS KESEHATAN KABUPATEN BOGOR | B21: 1368901403000 | E21: 18/06/2025 | I21: =J21+L21 -> 688200 | J21: 620000 | K21: 568333 | L21: 68200 | O21: =J21*1.5% -> 9300 | P21: =J21+M21-O21 -> 610700 | S21: 2.0025002e+15
A22: DINAS KESEHATAN KABUPATEN BOGOR | B22: 1368901403000 | E22: 18/06/2025 | I22: =J22+L22 -> 4384500 | J22: 3950000 | K22: 3620833 | L22: 434500 | O22: =J22*1.5% -> 59250 | P22: =J22+M22-O22 -> 3890750 | S22: 2.0125002e+15
A23: DINAS KESEHATAN KABUPATEN BOGOR | B23: 1368901403000 | E23: 20/06/2025 | I23: =J23+L23 -> 8074140 | J23: 7274000 | K23: 6667834 | L23: 800140 | O23: =J23*1.5% -> 109110 | P23: =J23+M23-O23 -> 7164890 | S23: 2.0025002e+15
A24: DINAS KESEHATAN KABUPATEN BOGOR | B24: 1368901403000 | E24: 20/06/2025 | I24: =J24+L24 -> 3406000 | J24: 3068468 | K24: 2812763 | L24: 337532 | O24: =J24*1.5% -> 46027.02 | P24: =J24+M24-O24 -> 3022441 | S24: 2.0025002e+15
A25: DINAS KESEHATAN KABUPATEN BOGOR | B25: 1368901403000 | E25: 20/06/2025 | I25: =J25+L25 -> 6993000 | J25: 6300000 | K25: 5775000 | L25: 693000 | O25: =J25*1.5% -> 94500 | P25: =J25+M25-O25 -> 6205500 | S25: 2.0025002e+15
A26: DINAS KESEHATAN KABUPATEN BOGOR | B26: 1368901403000 | E26: 20/06/2025 | I26: =J26+L26 -> 31689997 | J26: 28549547 | K26: 26170419 | L26: 3140450 | O26: =J26*1.5% -> 428243.21 | P26: =J26+M26-O26 -> 28121304 | S26: 2.0025002e+15
A27: DINAS KESEHATAN KABUPATEN BOGOR | B27: 1368901403000 | E27: 24/06/2025 | I27: =J27+L27 -> 2763900 | J27: 2490000 | K27: 2282500 | L27: 273900 | O27: =J27*1.5% -> 37350 | P27: =J27+M27-O27 -> 2452650 | S27: 2.0025002e+15
A28: DINAS KESEHATAN KABUPATEN BOGOR | B28: 1368901403000 | E28: 45695 | I28: =J28+L28 -> 17040029 | J28: 15351380 | K28: 14072072 | L28: 1688649 | O28: =J28*1.5% -> 230270.7 | P28: =J28+M28-O28 -> 15121109 | S28: 2.0025002e+15
A29: PUSAT KESEHATAN MASYARAKAT BOGOR TENGAH KOTA BOGOR | B29: 606032910404000 | E29: 45754 | I29: =J29+L29 -> 300000 | J29: 270270 | K29: 247748 | L29: 29730 | O29: =J29*1.5% -> 4054.05 | P29: =J29+M29-O29 -> 266215.95 | S29: 2.0025002e+15
A30: RUMAH SAKIT UMUM DAERAH CIBINONG KABUPATEN BOGOR | B30: 656901832403000 | E30: 45876 | I30: =J30+L30 -> 72014070 | J30: 64877541 | K30: 59471079 | L30: 7136529 | O30: =J30*1.5% -> 973163.11 | P30: =J30+M30-O30 -> 63904378 | S30: 2.0025002e+15
A31: RUMAH SAKIT UMUM DAERAH CIBINONG KABUPATEN BOGOR | B31: 656901832403000 | E31: 45876 | I31: =J31+L31 -> 80066790 | J31: 72132243 | K31: 66121223 | L31: 7934547 | O31: =J31*1.5% -> 1081983.6 | P31: =J31+M31-O31 -> 71050259 | S31: 2.0025002e+15
A32: DINAS KESEHATAN KABUPATEN BOGOR | B32: 1368901403000 | E32: 15/07/2025 | I32: =J32+L32 -> 12699009 | J32: 11440550 | K32: 10487162 | L32: 1258459 | O32: =J32*1.5% -> 171608.25 | P32: =J32+M32-O32 -> 11268942 | S32: 2.0025002e+15
A33: DINAS KESEHATAN KABUPATEN BOGOR | B33: 1368901403000 | E33: 17/07/2025 | I33: =J33+L33 -> 8731260 | J33: 7866000 | K33: 7210500 | L33: 865260 | O33: =J33*1.5% -> 117990 | P33: =J33+M33-O33 -> 7748010 | S33: 2.0025002e+15
A34: DINAS KESEHATAN KABUPATEN BOGOR | B34: 1368901403000 | E34: 24/07/2025 | I34: =J34+L34 -> 38865469 | J34: 35013982 | K34: 32095721 | L34: 3851487 | O34: =J34*1.5% -> 525209.73 | P34: =J34+M34-O34 -> 34488772 | S34: 2.0025002e+15
A35: DINAS KESEHATAN KABUPATEN BOGOR | B35: 1368901403000 | E35: 28/07/2025 | I35: =J35+L35 -> 7152840 | J35: 6444000 | K35: 5907001 | L35: 708840 | O35: =J35*1.5% -> 96660 | P35: =J35+M35-O35 -> 6347340 | S35: 2.0025002e+15
A36: DINAS KESEHATAN KABUPATEN BOGOR | B36: 1368901403000 | E36: 13/08/2025 | I36: =J36+L36 -> 10782362 | J36: 9898200 | K36: 9073347 | L36: 884162 | O36: =J36*1.5% -> 148473 | P36: =J36+M36-O36 -> 9749727 | S36: 2.0025002e+15
A37: DINAS KESEHATAN KABUPATEN BOGOR | B37: 1368901403000 | E37: 13/08/2025 | I37: =J37+L37 -> 28081023 | J37: 25298241 | K37: 23189849 | L37: 2782782 | O37: =J37*1.5% -> 379473.61 | P37: =J37+M37-O37 -> 24918767 | S37: 2.0025003e+15
A38: DINAS KESEHATAN KABUPATEN BOGOR | B38: 1368901403000 | E38: 15/08/2025 | I38: =J38+L38 -> 8752855 | J38: 7908848 | K38: 7249759 | L38: 844007 | O38: =J38*1.5% -> 118632.72 | P38: =J38+M38-O38 -> 7790215.3 | S38: 2.0025003e+15
A39: DINAS KESEHATAN KABUPATEN BOGOR | B39: 1368901403000 | E39: 22/08/2025 | I39: =J39+L39 -> 8308380 | J39: 7894820 | K39: 7236878 | L39: 413560 | O39: =J39*1.5% -> 118422.3 | P39: =J39+M39-O39 -> 7776397.7 | S39: 2.0025003e+15
A40: DINAS KESEHATAN KABUPATEN BOGOR | B40: 1368901403000 | E40: 22/08/2025 | I40: =J40+L40 -> 2230001 | J40: 2009010 | K40: 1841592 | L40: 220991 | O40: =J40*1.5% -> 30135.15 | P40: =J40+M40-O40 -> 1978874.9 | S40: 2.0025003e+15
A41: DINAS KESEHATAN KABUPATEN BOGOR | B41: 1368901403000 | E41: 29/08/2025 | I41: =J41+L41 -> 10043002 | J41: 9047750 | K41: 8293768 | L41: 995252 | O41: =J41*1.5% -> 135716.25 | P41: =J41+M41-O41 -> 8912033.8 | S41: 2.0025003e+15
A42: DINAS KESEHATAN KABUPATEN BOGOR | B42: 1368901403000 | E42: 29/08/2025 | I42: =J42+L42 -> 11147730 | J42: 10043000 | K42: 9206083 | L42: 1104730 | O42: =J42*1.5% -> 150645 | P42: =J42+M42-O42 -> 9892355 | S42: 2.0025003e+15
A43: Puskesmas BLUD Saketi | B43: 1091031211360357 | E43: 29/08/2025 | I43: =J43+L43 -> 5182043 | J43: 4668510 | K43: 4279440 | L43: 513533 | O43: =J43*1.5% -> 70027.65 | P43: =J43+M43-O43 -> 4598482.3 | S43: 2.0125003e+15
A44: DINAS KESEHATAN KABUPATEN BOGOR | B44: 1368901403000 | E44: 45666 | I44: =J44+L44 -> 31169688 | J44: 28080800 | K44: 25740733 | L44: 3088888 | O44: =J44*1.5% -> 421212 | P44: =J44+M44-O44 -> 27659588 | S44: 2.0025003e+15
A45: RUMAH SAKIT UMUM DAERAH CIBINONG KABUPATEN BOGOR | B45: 656901832403000 | E45: 15/09/2025 | I45: =J45+L45 -> 105979615 | J45: 95477131 | K45: 87520703 | L45: 10502484 | O45: =J45*1.5% -> 1432157 | P45: =J45+M45-O45 -> 94044974 | S45: 2.0025003e+15
A46: Puskesmas Pasir Angin | B46: 1368901403000 | E46: 15/09/2025 | I46: =J46+L46 -> 2289467 | J46: 2044167 | K46: 2044167 | L46: 245300 | O46: =J46*1.5% -> 30662.505 | P46: =J46+M46-O46 -> 2013504.5 | S46: 2.0025003e+15
A47: DINAS KESEHATAN KABUPATEN BOGOR | B47: 1368901403000 | E47: 19/09/2025 | I47: =J47+L47 -> 954600 | J47: 860000 | K47: 788333 | L47: 94600 | O47: =J47*1.5% -> 12900 | P47: =J47+M47-O47 -> 847100 | S47: 2.0025003e+15
A48: PUSKESMAS CIPEUCANG | B48: 1091031211062312 | E48: 23/09/2025 | I48: =J48+L48 -> 3098149 | J48: 2791125 | K48: 2558532 | L48: 307024 | O48: =J48*1.5% -> 41866.875 | P48: =J48+M48-O48 -> 2749258.1 | S48: 3.0025003e+15
A49: PUSKESMAS CIPEUCANG | B49: 1091031211062312 | E49: 24/09/2025 | I49: =J49+L49 -> 2066784 | J49: 1861968 | K49: 1706804 | L49: 204816 | O49: =J49*1.5% -> 27929.52 | P49: =J49+M49-O49 -> 1834038.5 | S49: 3.0025003e+15
A50: PERTAMINA BINA MEDIKA IHC | B50: 10611671051000 | E50: 25/09/2025 | I50: =J50+L50 -> 4050000 | J50: 4050000 | K50: 3712500 | M50: 445500 | O50: =J50*1.5% -> 60750 | P50: =J50+M50-O50 -> 4434750 | S50: 3.0025003e+15
A51: PERTAMINA BINA MEDIKA IHC | B51: 10611671051000 | E51: 25/09/2025 | I51: =J51+L51 -> 4050000 | J51: 4050000 | K51: 3712500 | M51: 445500 | O51: =J51*1.5% -> 60750 | P51: =J51+M51-O51 -> 4434750 | S51: 2.0225003e+15
A52: PERTAMINA BINA MEDIKA IHC | B52: 10611671051000 | E52: 25/09/2025 | I52: =J52+L52 -> 8100000 | J52: 8100000 | K52: 7425000 | M52: 891000 | O52: =J52*1.5% -> 121500 | P52: =J52+M52-O52 -> 8869500 | S52: 2.0025003e+15
A53: DINAS KESEHATAN KABUPATEN BOGOR | B53: 1368901403000 | E53: 26/09/2025 | I53: =J53+L53 -> 281081 | J53: 281081 | K53: 257658 | M53: 30919 | O53: =J53*1.5% -> 4216.215 | P53: =J53+M53-O53 -> 307783.78 | S53: 2.0025003e+15
A54: DINAS KESEHATAN KABUPATEN BOGOR | B54: 1368901403000 | E54: 26/09/2025 | I54: =J54+L54 -> 2727736 | J54: 2457398 | K54: 2252820 | L54: 270338 | O54: =J54*1.5% -> 36860.97 | P54: =J54+M54-O54 -> 2420537 | S54: 2.0025003e+15
A55: DINAS KESEHATAN KABUPATEN BOGOR | B55: 1368901403000 | E55: 26/09/2025 | I55: =J55+L55 -> 11166600 | J55: 10060000 | K55: 9221667 | L55: 1106600 | O55: =J55*1.5% -> 150900 | P55: =J55+M55-O55 -> 9909100 | S55: 2.0025003e+15
A56: DINAS KESEHATAN KABUPATEN BOGOR | B56: 1368901403000 | E56: 26/09/2025 | I56: =J56+L56 -> 3803526 | J56: 3426600 | K56: 3141050 | L56: 376926 | O56: =J56*1.5% -> 51399 | P56: =J56+M56-O56 -> 3375201 | S56: 4.0025003e+15
A57: DINAS KESEHATAN KABUPATEN BOGOR | B57: 1368901403000 | E57: 26/09/2025 | I57: =J57+L57 -> 19701390 | J57: 17749000 | K57: 16269917 | L57: 1952390 | O57: =J57*1.5% -> 266235 | P57: =J57+M57-O57 -> 17482765 | S57: 2.0025003e+15
A58: DINAS KESEHATAN KABUPATEN BOGOR | B58: 1368901403000 | E58: 26/09/2025 | I58: =J58+L58 -> 8778819 | J58: 7908848 | K58: 7249759 | L58: 869971 | O58: =J58*1.5% -> 118632.72 | P58: =J58+M58-O58 -> 7790215.3 | S58: 2.0025003e+15
A59: DINAS KESEHATAN KABUPATEN BOGOR | B59: 1368901403000 | E59: 29/09/2025 | I59: =J59+L59 -> 22021290 | J59: 19839000 | K59: 18185750 | L59: 2182290 | O59: =J59*1.5% -> 297585 | P59: =J59+M59-O59 -> 19541415 | S59: 2.0025003e+15
A60: DINAS KESEHATAN KABUPATEN BOGOR | B60: 1368901403000 | E60: 29/09/2025 | I60: =J60+L60 -> 9251295 | J60: 8334500 | K60: 7639958 | L60: 916795 | O60: =J60*1.5% -> 125017.5 | P60: =J60+M60-O60 -> 8209482.5 | S60: 4.0025003e+15
A61: DINAS KESEHATAN KABUPATEN BOGOR | B61: 1368901403000 | E61: 29/09/2025 | I61: =J61+L61 -> 8040202 | J61: 7243420 | K61: 6639848 | L61: 796782 | O61: =J61*1.5% -> 108651.3 | P61: =J61+M61-O61 -> 7134768.7 | S61: 2.0025003e+15
A62: Puskesmas Pasir Angin | B62: 1368901403000 | E62: 29/09/2025 | I62: =J62+L62 -> 8996885 | J62: 8032933 | K62: 8032933 | L62: 963952 | O62: =J62*1.5% -> 120493.99 | P62: =J62+M62-O62 -> 7912439 | S62: 2.0125003e+15
A63: DINAS KESEHATAN KABUPATEN BOGOR | B63: 1368901403000 | E63: 30/09/2025 | I63: =J63+L63 -> 504000 | J63: 504000 | K63: 462000 | M63: 55440 | O63: =J63*1.5% -> 7560 | P63: =J63+M63-O63 -> 551880 | S63: 2.0125003e+15
A64: RUMAH SAKIT UMUM DAERAH CIBINONG KABUPATEN BOGOR | B64: 656901832403000 | E64: 45879 | I64: =J64+L64 -> 25015692 | J64: 22536660 | K64: 20658604 | L64: 2479032 | O64: =J64*1.5% -> 338049.9 | P64: =J64+M64-O64 -> 22198610 | S64: 2.0125003e+15
A65: DINAS KESEHATAN KABUPATEN TASIKMALAYA | B65: 630922045425000 | E65: 14/10/2025 | I65: =J65+L65 -> 3496240 | J65: 3149766 | K65: 2887284 | L65: 346474 | O65: =J65*1.5% -> 47246.49 | P65: =J65+M65-O65 -> 3102519.5 | S65: 2.0125003e+15
A66: DINAS KESEHATAN KABUPATEN TASIKMALAYA | B66: 630922045425000 | E66: 14/10/2025 | I66: =J66+L66 -> 3993480 | J66: 3597729 | K66: 3297918 | L66: 395751 | O66: =J66*1.5% -> 53965.935 | P66: =J66+M66-O66 -> 3543763.1 | S66: 2.0125003e+15
A67: DINAS KESEHATAN KABUPATEN TASIKMALAYA | B67: 630922045425000 | E67: 14/10/2025 | I67: =J67+L67 -> 1900000 | J67: 1711712 | K67: 1569069 | L67: 188288 | O67: =J67*1.5% -> 25675.68 | P67: =J67+M67-O67 -> 1686036.3 | S67: 2.0025003e+15
A68: DINAS KESEHATAN KABUPATEN TASIKMALAYA | B68: 630922045425000 | E68: 14/10/2025 | I68: =J68+L68 -> 1900000 | J68: 1711712 | K68: 1569069 | L68: 188288 | O68: =J68*1.5% -> 25675.68 | P68: =J68+M68-O68 -> 1686036.3 | S68: 2.0025003e+15
A69: DINAS KESEHATAN KABUPATEN TASIKMALAYA | B69: 630922045425000 | E69: 14/10/2025 | I69: =J69+L69 -> 1900000 | J69: 1711712 | K69: 1569069 | L69: 188288 | O69: =J69*1.5% -> 25675.68 | P69: =J69+M69-O69 -> 1686036.3 | S69: 2.0225003e+15
A70: DINAS KESEHATAN KABUPATEN TASIKMALAYA | B70: 630922045425000 | E70: 14/10/2025 | I70: =J70+L70 -> 1900000 | J70: 1711712 | K70: 1569069 | L70: 188288 | O70: =J70*1.5% -> 25675.68 | P70: =J70+M70-O70 -> 1686036.3 | S70: 2.0025003e+15
A71: DINAS KESEHATAN KABUPATEN TASIKMALAYA | B71: 630922045425000 | E71: 14/10/2025 | I71: =J71+L71 -> 1900000 | J71: 1711712 | K71: 1569069 | L71: 188288 | O71: =J71*1.5% -> 25675.68 | P71: =J71+M71-O71 -> 1686036.3 | S71: 2.0025003e+15
A72: Puskesmas Gandoang | B72: 1368901403000 | E72: 16/10/2025 | I72: =J72+L72 -> 7436578 | J72: 6639802 | K72: 6639802 | L72: 796776 | O72: =J72*1.5% -> 99597.03 | P72: =J72+M72-O72 -> 6540205 | S72: 2.0025003e+15
A73: RUMAH SAKIT UMUM DAERAH CIBINONG KABUPATEN BOGOR | B73: 656901832403000 | E73: 16/10/2025 | I73: =J73+L73 -> 13300000 | J73: 11981982 | K73: 10983484 | L73: 1318018 | O73: =J73*1.5% -> 179729.73 | P73: =J73+M73-O73 -> 11802252 | S73: 3.0025003e+15
A74: RUMAH SAKIT UMUM DAERAH CIBINONG KABUPATEN BOGOR | B74: 656901832403000 | E74: 17/10/2025 | I74: =J74+L74 -> 101399620 | J74: 91351009 | K74: 83738425 | L74: 10048611 | O74: =J74*1.5% -> 1370265.1 | P74: =J74+M74-O74 -> 89980744 | S74: 3.0025003e+15
A75: PUSAT KESEHATAN MASYARAKAT KELAPA DUA KABUPATEN TANGERANG | B75: 963133392452000 | E75: 17/10/2025 | I75: =J75+L75 -> 16510441 | J75: 14874271 | K75: 13634749 | L75: 1636170 | O75: =J75*1.5% -> 223114.07 | P75: =J75+M75-O75 -> 14651157 | S75: 3.0025003e+15
A76: RUMAH SAKIT UMUM DAERAH CIBINONG KABUPATEN BOGOR | B76: 656901832403000 | E76: 17/10/2025 | I76: =J76+L76 -> 26259000 | J76: 23656757 | K76: 21685360 | L76: 2602243 | O76: =J76*1.5% -> 354851.35 | P76: =J76+M76-O76 -> 23301906 | S76: 3.0025003e+15
... A80: RUMAH SAKIT UMUM DAERAH CIBINONG KABUPATEN BOGOR | B80: 656901832403000 | E80: 22/10/2025 | I80: =J80+L80 -> 55806908 | J80: 50276494 | K80: 46086787 | L80: 5530414 | O80: =J80*1.5% -> 754147.41 | P80: =J80+M80-O80 -> 49522347 | S80: 2.0025003e+15
A81: PERTAMINA BINA MEDIKA IHC | B81: 10611671051000 | E81: 22/10/2025 | I81: =J81+L81 -> 5062500 | J81: 5062500 | K81: 4640625 | M81: 556875 | O81: =J81*1.5% -> 75937.5 | P81: =J81+M81-O81 -> 5543437.5 | S81: 2.0025003e+15
A82: PERTAMINA BINA MEDIKA IHC | B82: 10611671051000 | E82: 22/10/2025 | I82: =J82+L82 -> 6075000 | J82: 6075000 | K82: 5568750 | M82: 668250 | O82: =J82*1.5% -> 91125 | P82: =J82+M82-O82 -> 6652125 | S82: 2.0025003e+15
A83: PERTAMINA BINA MEDIKA IHC | B83: 10611671051000 | E83: 22/10/2025 | I83: =J83+L83 -> 6075000 | J83: 6075000 | K83: 5568750 | M83: 668250 | O83: =J83*1.5% -> 91125 | P83: =J83+M83-O83 -> 6652125 | S83: 2.0025003e+15
A84: PERTAMINA BINA MEDIKA IHC | B84: 10611671051000 | E84: 22/10/2025 | I84: =J84+L84 -> 6075000 | J84: 6075000 | K84: 5568750 | M84: 668250 | O84: =J84*1.5% -> 91125 | P84: =J84+M84-O84 -> 6652125 | S84: 2.0025003e+15
A85: PERTAMINA BINA MEDIKA IHC | B85: 10611671051000 | E85: 22/10/2025 | I85: =J85+L85 -> 8100000 | J85: 8100000 | K85: 7425000 | M85: 891000 | O85: =J85*1.5% -> 121500 | P85: =J85+M85-O85 -> 8869500 | S85: 2.0025003e+15
A86: DINAS KESEHATAN KABUPATEN BOGOR | B86: 1368901403000 | E86: 22/10/2025 | I86: =J86+L86 -> 14328713 | J86: 12908750 | K86: 11833021 | L86: 1419963 | O86: =J86*1.5% -> 193631.25 | P86: =J86+M86-O86 -> 12715119 | S86: 2.0025003e+15
A87: DINAS KESEHATAN KABUPATEN BOGOR | B87: 1368901403000 | E87: 22/10/2025 | I87: =J87+L87 -> 5189250 | J87: 4675000 | K87: 4285417 | L87: 514250 | O87: =J87*1.5% -> 70125 | P87: =J87+M87-O87 -> 4604875 | S87: 2.0025003e+15
A88: DINAS KESEHATAN KABUPATEN BOGOR | B88: 1368901403000 | E88: 22/10/2025 | I88: =J88+L88 -> 7401447 | J88: 6667970 | K88: 6112306 | L88: 733477 | O88: =J88*1.5% -> 100019.55 | P88: =J88+M88-O88 -> 6567950.5 | S88: 2.0025003e+15
A89: RUMAH SAKIT UMUM DAERAH PASAR MINGGU PROVINSI DKI JAKARTA | B89: 2783306017000 | E89: 22/10/2025 | I89: =J89+L89 -> 18315000 | J89: 16500000 | K89: 15125000 | L89: 1815000 | O89: =J89*1.5% -> 247500 | P89: =J89+M89-O89 -> 16252500 | S89: 2.0025003e+15
A90: DINES KESEHATAN KABUPATEN BOGOR | B90: 1368901403000 | E90: 22/10/2025 | I90: 1.0430043e+08 | J90: 93964354 | K90: =J90*11/12 -> 86133991 | L90: =J90*11% -> 10336079 | O90: =J90*1.5% -> 1409465.3 | P90: =J90+M90-O90 -> 92554889 | S90: 2.0125003e+15
A91: DINAS KESEHATAN KABUPATEN BOGOR | B91: 1368901403000 | E91: 24/10/2025 | I91: =J91+L91 -> 3542787 | J91: 3191700 | K91: 2925725 | L91: 351087 | O91: =J91*1.5% -> 47875.5 | P91: =J91+M91-O91 -> 3143824.5 | S91: 2.0125003e+15
A92: DINAS KESEHATAN KABUPATEN BOGOR | B92: 1368901403000 | E92: 24/10/2025 | I92: =J92+L92 -> 1498500 | J92: 1350000 | K92: 1237500 | L92: 148500 | O92: =J92*1.5% -> 20250 | P92: =J92+M92-O92 -> 1329750 | S92: 2.0225003e+15
A93: DINAS KESEHATAN KABUPATEN TASIKMALAYA | B93: 630922045425000 | E93: 27/10/2025 | I93: =J93+L93 -> 42772100 | J93: 38533423 | K93: 35322305 | L93: 4238677 | O93: =J93*1.5% -> 578001.34 | P93: =J93+M93-O93 -> 37955422 | S93: 2.0025004e+15
A94: DINAS KESEHATAN KABUPATEN TASIKMALAYA | B94: 630922045425000 | E94: 27/10/2025 | I94: =J94+L94 -> 3337000 | J94: 3006306 | K94: 2755781 | L94: 330694 | O94: =J94*1.5% -> 45094.59 | P94: =J94+M94-O94 -> 2961211.4 | S94: 2.0025004e+15
A95: DINAS KESEHATAN KABUPATEN TASIKMALAYA | B95: 630922045425000 | E95: 30/10/2025 | I95: =J95+L95 -> 11550000 | J95: 10405405 | K95: 9538287 | L95: 1144595 | O95: =J95*1.5% -> 156081.08 | P95: =J95+M95-O95 -> 10249324 | S95: 2.0025004e+15
A96: DINAS KESEHATAN KABUPATEN TASIKMALAYA | B96: 630922045425000 | E96: 30/10/2025 | I96: =J96+L96 -> 2135228 | J96: 1923629 | K96: 1763326 | L96: 211599 | O96: =J96*1.5% -> 28854.435 | P96: =J96+M96-O96 -> 1894774.6 | S96: 2.0025004e+15
A97: Puskesmas Bojonggede | B97: 324970403000 | E97: 45727 | I97: =J97+L97 -> 4799667 | J97: 4285417 | K97: 4285417 | L97: 514250 | O97: =J97*1.5% -> 64281.255 | P97: =J97+M97-O97 -> 4221135.7 | S97: 2.0025004e+15
A98: DINAS KESEHATAN KABUPATEN BOGOR | B98: 1368901403000 | E98: 14/11/2025 | I98: =J98+L98 -> 136676924 | J98: 123132364 | K98: 112871334 | L98: 13544560 | O98: =J98*1.5% -> 1846985.5 | P98: =J98+M98-O98 -> 1.2128538e+08 | S98: 2.0025004e+15
A99: DINAS KESEHATAN KABUPATEN BOGOR | B99: 1368901403000 | E99: 17/11/2025 | I99: =J99+L99 -> 2564100 | J99: 2310000 | K99: 2117500 | L99: 254100 | O99: =J99*1.5% -> 34650 | P99: =J99+M99-O99 -> 2275350 | S99: 2.0025004e+15
A100: DINAS KESEHATAN KABUPATEN BOGOR | B100: 1368901403000 | E100: 17/11/2025 | I100: =J100+L100 -> 1998000 | J100: 1800000 | K100: 1650000 | L100: 198000 | O100: =J100*1.5% -> 27000 | P100: =J100+M100-O100 -> 1773000 | S100: 3.0025004e+15
A101: DINAS KESEHATAN KABUPATEN BOGOR | B101: 1368901403000 | E101: 17/11/2025 | I101: =J101+L101 -> 467754 | J101: 421400 | K101: 386283 | L101: 46354 | O101: =J101*1.5% -> 6321 | P101: =J101+M101-O101 -> 415079 | S101: 2.0125004e+15
A102: RUMAH SAKIT UMUM DAERAH CIBINONG KABUPATEN BOGOR | B102: 656901832403000 | E102: 18/11/2025 | I102: =J102+L102 -> 1675545 | J102: 1509500 | K102: 1383708 | L102: 166045 | O102: =J102*1.5% -> 22642.5 | P102: =J102+M102-O102 -> 1486857.5 | S102: 3.0125004e+15
A103: PUSAT KESEHATAN MASYARAKAT KECAMATAN TANJUNG PRIOK - JAKARTA UTARA PROVINSI DKI JAKARTA | B103: 1247048048000 | E103: 25/11/2025 | I103: =J103+L103 -> 3885000 | J103: 3500000 | K103: 3208333 | L103: 385000 | O103: =J103*1.5% -> 52500 | P103: =J103+M103-O103 -> 3447500 | S103: 4.0025004e+15
A104: PUSAT KESEHATAN MASYARAKAT KECAMATAN TANJUNG PRIOK - JAKARTA UTARA PROVINSI DKI JAKARTA | B104: 1247048048000 | E104: 25/11/2025 | I104: =J104+L104 -> 12654000 | J104: 11400000 | K104: 10450000 | L104: 1254000 | O104: =J104*1.5% -> 171000 | P104: =J104+M104-O104 -> 11229000 | S104: 2.0025004e+15
...

Sheet PURCHASES
A1: MPG BCA | B1: 4788883330
J2: Barang dan Jasa | K2: Jasa | N2: lampirkan link filenya disini
A3: Code | B3: Suppliers | C3: Item | D3: Date | E3: Sales Order | F3: PO No. | G3: Date Inv. | H3: Invoice | I3: Amount | J3: VAT | K3: PPH 23 | L3: A/P | M3: Date Invoice | N3: Link Document | O3: Status | P3: Remark
B4: Tokopedia | C4: Pembelian Termometer PKM Balekambang | G4: 45816 | I4: 705700 | L4: =I4+J4 -> 705700 | M4: =MONTH(G4) -> 6 | N4: Pembelian Termometer PKM | O4: Approved
B5: Shopee | C5: Pembelian Kursi, Meja dan Lemari PKM Gandoang | G5: 45882 | I5: 11381600 | L5: =I5+J5 -> 11381600 | M5: =MONTH(G5) -> 8 | N5: Pembelian Pesanan PKM Gandoang.pdf | O5: Approved
B6: Shopee | C6: Pembelian Composit Resin, Umblical, Bonding, Gludaten, Bisturi PKM DPT Saketi | E6: SURAT PESANAN PKM DPT SAKETI.jpeg | G6: 45882 | I6: 2654410 | L6: =I6+J6 -> 2654410 | M6: =MONTH(G6) -> 8 | N6: PKM DPT SAKETI.pdf | O6: Approved | Q6: 1322000
B7: PT. Top Point Medical | C7: TP Infusion Set Advance | E7: Surat Pesanan RSPP | F7: PO Infusion Set - Top Point | G7: 45880 | I7: 3040541 | J7: =I7*11% -> 334459.51 | L7: =I7+J7 -> 3375000.5 | M7: =MONTH(G7) -> 8 | N7: Invoice Top Point | O7: Approved | P7: FP Infusion Set - Top Point
B8: Shopee | C8: Pembelian Gludenta DPT Saketi | E8: part of SO no.3 | G8: 45882 | I8: 1408256 | L8: =I8+J8 -> 1408256 | M8: =MONTH(G8) -> 8 | N8: Gludenta | O8: Approved
B9: Top Point | C9: Pembelian Suntikan DPT Saketi | E9: part of SO no.3 | G9: 45888 | I9: 136554 | J9: =I9*11% -> 15020.94 | L9: =I9+J9 -> 151574.94 | M9: =MONTH(G9) -> 8 | N9: 22-08-1015 (pembelian top point) | O9: Approved | P9: FP - Top Point.pdf
B10: Sarana Megamedilab Sejahtera (SMS) | C10: Pembelian Lampu | E10: RSUD Cibinong | G10: 45869 | I10: 2800000 | J10: =I10*11% -> 308000 | L10: 3108000 | M10: =MONTH(G10) -> 7 | N10: Invoice SMS | O10: Approved | P10: FP - PT. SMS
B11: Shopee | C11: Pembelian Pesanan Plastik (PKM Cimandala) | E11: -Menyusul- | G11: 45895 | I11: 2021100 | L11: 2021100 | M11: =MONTH(G11) -> 8 | N11: Pesanan PKM Cimandala | O11: Approved
B12: Shopee | C12: Pembelian Yellow dan Blue Tip (PKM Cangkurawok) | E12: surat-pesanan-EP-01K387EQ0896Y44BX6R9RSJ2FA (Pkm Cangkurawok) | G12: 45895 | I12: 82499 | L12: 82499 | M12: =MONTH(G12) -> 8 | N12: Pembelanjaan yellow dan blue tip (pkm cangkurawok) 26/8/25 | O12: Approved
B13: Shopee | C13: Pembelanjaan Pesanan (PKM Pasir Angin) | E13: surat-pesanan-EP-01K381B70E6329EG57Q86XG5DH.pdf (PKM Pasir angin) 27-08-25 | G13: 45896 | I13: 1086000 | L13: 1086000 | M13: =MONTH(G13) -> 8 | N13: Pembelanjaan Pesanan PKM Pasir Angin 27-08-25 | O13: Approved
B14: Top Point | C14: Pembelian TP Infusion Set Advance (RSPP) | E14: Surat Pesanan RSPP PO 2 (20-08-25) | F14: PO ke Top Point (20-08-25) | G14: 45890 | I14: 3040541 | J14: 334459 | L14: =I14+J14 -> 3375000 | M14: =MONTH(G14) -> 8 | N14: Invoice TP (21-08-25) | O14: Approved | P14: FP - Top Point (21-08-25)
B15: PT Demaz Noer Abadi | C15: Pembelian Pesanan (PKM Karyamekar) Test Strip | E15: Pesanan PKM Karya Mekar (28-08-25) | F15: PO MPG-270825008 Biosensor.pdf | G15: 45897 | I15: 700000 | J15: 77000 | L15: =I15+J15 -> 777000 | M15: =MONTH(G15) -> 8 | N15: inv biosensor | O15: Approved | P15: follow up FPnya danis
B16: PT. Elba Lab Medika | C16: Pembelian Pesanan (PKM Ciawi ) Uric acid dan Glucose | E16: surat-pesanan-EP-01K3Q5WHEXQ3VZNQBKWARSAMDH Pkm Ciawi Erba.pdf | F16: PO MPG-270825006 Elba Medika Revisi.pdf | G16: 45896 | I16: 6088810 | J16: 669769 | L16: =I16+J16 -> 6758579 | M16: =MONTH(G16) -> 8 | N16: Inv Elba | O16: Approved | P16: follow up FPnya danis
B17: Shopee | C17: Pembelian Pesanan (PKM Karyamekar) Alcohol swab, blue dan yellow tip | E17: part of SO no.15 | G17: 45896 | I17: 206508 | L17: =I17+J17 -> 206508 | M17: =MONTH(G17) -> 8 | N17: Pembelanjaan PKM Karyamekar (sp 27-08-25) | O17: Approved
B18: Shopee | C18: Pembelian Pesanan (PKM Pasir Angin) Apar 3kg | E18: surat-pesanan-EP-01K3T38R3TQ03RS3GZPYQRVWJ9 PKM Pasir Angin (Apar) | G18: 45898 | I18: 541000 | L18: =I18+J18 -> 541000 | M18: =MONTH(G18) -> 8 | N18: PKM Pasir Angin - Apar 3kg | O18: Approved
B19: PT. Burhan Sejahtera Mulia | C19: Pembelian Pesanan (PKM Karyamekar) Vacum Tube Plain | E19: Patt of SO np.15 | F19: PO ke PT. BSM (vacum tube) | G19: 45898 | I19: 425000 | J19: 46750 | L19: =I19+J19 -> 471750 | M19: =MONTH(G19) -> 8 | N19: inv bsm (vacume tube) | O19: Approved | P19: fp akan di fu setelah barang tiba
B20: Shopee | C20: Pembelian Pesanan (PKM Bojong) cover glass dan bisturi | E20: Surat Pesanan PKM Bojong (3 Sep 2025) | G20: 45903 | I20: 96580 | L20: =I20+J20 -> 96580 | M20: =MONTH(G20) -> 9 | N20: Bisturi dan Cover glass PKM Bojong | O20: Approved
B21: Shopee | C21: Pembelian Pesanan (PKM Bojong) kassa steril | E21: Surat Pesanan PKM Bojong (3 Sep 2025) | G21: 45903 | I21: 402500 | L21: =I21+J21 -> 402500 | M21: =MONTH(G21) -> 9 | N21: Kassa Steril PKM Bojong | O21: Approved
B22: Toko Pramuka | C22: Pembelian Pesanan (PKM Sentul) 10box Safeguard | E22: -Menyusul- | G22: 45903 | I22: 430000 | L22: =I22+J22 -> 430000 | M22: =MONTH(G22) -> 9 | N22: Safeguard PKM Sentul | O22: Approved | P22: ditunda dl
B23: Top Point | C23: Pembelian Pesanan (RSPP) PO ke 3 | E23: Surat Pesanan RSPP (PO 3) | F23: PO ke Top Point (Pesanan RSPP PO 3) | G23: 45896 | I23: 6081081 | J23: 668919 | L23: =I23+J23 -> 6750000 | M23: =MONTH(G23) -> 8 | N23: Inv TP (PO 3 RSPP) | O23: Approved | P23: FP - Top Point (PO 3 RSPP)
B24: Top Point | C24: Pembelian Kekurangan Stock Suntikan RSUD | E24: Surat Pesanan Suntikan RSUD Cibinong | F24: PO ke TOP POINT (stok suntikan rsud) | G24: 45897 | I24: 3386086 | J24: 372469 | L24: =I24+J24 -> 3758555 | M24: =MONTH(G24) -> 8 | N24: Inv TP (stok suntikan rsud) | O24: Approved | P24: FP TP (stok suntikan rsud)
B25: Sarana Megamedilab Sejahtera (SMS) | C25: Pembelian Reagen RSUD Cibinong (Nodin 15) | D25: SPH RSUD CIBINONG NODIN 15 (1).pdf | E25: nodin 15 rsud cibinong | F25: PO ke SMS (nodin 15 RSUD Cibinong) | G25: 45876 | I25: 12284010 | J25: 1351241 | L25: =I25+J25 -> 13635251 | M25: =MONTH(G25) -> 8 | N25: inv sms | O25: Approved | P25: FP SMS (nodin 15 RSUD Cibinong)
B26: PT. Burhan Sejahtera Mulia | C26: Pembelian Pesanan (PKM Bojong) Reagen Asam Urat | E26: part of SO no.20 | F26: PO MPG-080925003 BSM.pdf | G26: 45908 | I26: 720440 | J26: 79248 | L26: =I26+J26 -> 799688 | M26: =MONTH(G26) -> 9 | N26: Inv BSM | O26: Approved | P26: akan di follow up
B27: Shopee | C27: Pembelanjaan Pesanan Tambahan (PKM Bojong) Carpule dan Plastik Sampah Medis | E27: -Menyusul- | G27: 45908 | I27: 543000 | L27: =I27 -> 543000 | M27: =MONTH(G27) -> 9 | N27: Pesanan Tambahan PKM Bojong | O27: Approved
B28: PT. Tirta Investama | C28: Pembaayaran Aqua Galon Gedung | G28: 45900 | I28: 400000 | L28: =I28 -> 400000 | M28: =MONTH(G28) -> 8 | N28: inv aqua | O28: Approved | P28: fp aqua
B29: PT. Top Point Medical | C29: Pembellian Pesanan (RSPP) PO ke 4 | E29: PO KE 4 RSPP | F29: po ke tp (rspp ke 4) | G29: 45909 | I29: 4560811 | J29: 501689 | L29: =I29+J29 -> 5062500 | M29: =MONTH(G29) -> 9 | N29: INV TP : 034/TPM/IX/2025 | O29: Approved | P29: FP TP : 04002500280251436
B30: Gedung | C30: Pembayaran Listrik dan Parkir Gedung (pemakaian agustus) | G30: 45915 | I30: 4684781 | L30: =I30 -> 4684781 | M30: =MONTH(G30) -> 9 | N30: listrik parkir agustus.pdf | O30: Approved
B31: Shopee | C31: Pembelian Kekurangan Plastik Sampah Medis (PKM Bojong) | E31: NOTA PERABOT KANTOR MATA PENSIL 09 25.pdf | G31: 45915 | I31: 53380 | L31: =I31 -> 53380 | M31: =MONTH(G31) -> 9 | N31: Pembelian Kekurangan Plastik PKM Bojong | O31: Approved
B32: Shopee | C32: Pembelian Kontrol Kimia (PKM Balekambang) | E32: Pesanan Balekambang | G32: 45916 | I32: 1277500 | L32: =I32 -> 1277500 | M32: =MONTH(G32) -> 9 | N32: Kontrol Kimia | O32: Approved
B33: Shopee | C33: Pembelian Pesanan (PKM Cipeucang) | E33: Surat Pesanan BMHP PKM Cipeucang.pdf | G33: 45917 | I33: 2676315 | L33: =I33 -> 2676315 | M33: =MONTH(G33) -> 9 | N33: Pembelanjaan Pesanan PKM Cipeucang.pdf | O33: Approved
B34: Shopee | C34: Pembelian Pesanan (PKM Kelapa Dua) Plastik Sampah | E34: SP Belanja Kebersihan Puskesmas Kelapa Dua September 2025.pdf | G34: 45925 | I34: 1827490 | L34: 1827490 | M34: =MONTH(G34) -> 9 | N34: plastik sampah pkm kelapa dua.pdf | O34: Approved
B35: Shopee | C35: Pembelian Pesanan (PKM Kelapa Dua) Pengharum Ruangan spray dan gantung dahlia | E35: SP Belanja Kebersihan Puskesmas Kelapa Dua September 2025.pdf | G35: 45925 | I35: 937200 | L35: 937200 | M35: =MONTH(G35) -> 9 | N35: Pengahrum spray dan gantung Dahlia | O35: Approved
B36: Shopee | C36: Pembelian Pesanan (PKM Kelapa Dua) tissue livi dan paseo | E36: SP Belanja Kebersihan Puskesmas Kelapa Dua September 2025.pdf | G36: 45925 | I36: 480255 | L36: 480255 | M36: =MONTH(G36) -> 9 | N36: tissue livi dan paseo.pdf | O36: Approved
B37: Shopee | C37: Pembelian Pesanan (PKM Kelapa Dua) Baygon | E37: SP Belanja Kebersihan Puskesmas Kelapa Dua September 2025.pdf | G37: 45925 | I37: 798000 | L37: 798000 | M37: =MONTH(G37) -> 9 | N37: baygon.pdf | O37: Approved
B38: Shopee | C38: Pembelian Pesanan (PKM Kelapa Dua) switzal dan minyak telon | E38: SP Belanja Kebersihan Puskesmas Kelapa Dua September 2025.pdf | G38: 45925 | I38: 493200 | L38: 493200 | M38: =MONTH(G38) -> 9 | N38: switzal dan minyak telon.pdf | O38: Approved
B39: Shopee | C39: Pembelian Pesanan (PKM Kelapa Dua) kamper | E39: SP Belanja Kebersihan Puskesmas Kelapa Dua September 2025.pdf | G39: 45925 | I39: 622900 | L39: 622900 | M39: =MONTH(G39) -> 9 | N39: kamper dan pewangi kopi.pdf | O39: Approved
B40: Shopee | C40: Pembelian Pesanan (PKM Kelapa Dua) tempat sampah | E40: SP Belanja Kebersihan Puskesmas Kelapa Dua September 2025.pdf | G40: 45925 | I40: 432000 | L40: 432000 | M40: =MONTH(G40) -> 9 | N40: tempat sampah shinpo | O40: Approved
B41: Shopee | C41: Pembelian Pesanan (PKM Kelapa Dua) sapu,ember,sikat,keset,sapu plafon,air spray | E41: SP Belanja Kebersihan Puskesmas Kelapa Dua September 2025.pdf | G41: 45925 | I41: 601325 | L41: 601325 | M41: =MONTH(G41) -> 9 | N41: sikat,sapu,ember,keset,sapu plafon,automatic spray.pdf | O41: Approved
B42: PT. Top Point | C42: Pembelian Pesanan RSPP PO ke 5 | E42: Surat Pesanan RSPP Po 5 | F42: PO ke TP RSPP PO 5 | G42: 45918 | I42: 4560811 | J42: 501689 | L42: =I42+J42 -> 5062500 | M42: =MONTH(G42) -> 9 | N42: RSPP PO 5 | O42: Approved | P42: FP TP PO 5
B43: PT. Sangiang Karya Mandiri | C43: Pembelian Pesanan Dinkes Tasikmalaya | E43: SP 46 Genta (1).pdf | F43: po ke pt.sangiang | G43: 45925 | I43: 4375000 | J43: 481250 | L43: =I43+J43 -> 4856250 | M43: =MONTH(G43) -> 9 | N43: inv | O43: Approved | Q43: 1711712
B44: Shopee | C44: Pembelian Pesanan (PKM Kelapa Dua) mop pel, kain lap, sikat gagang | E44: SP Belanja Kebersihan Puskesmas Kelapa Dua September 2025.pdf | G44: 45925 | I44: 413664 | L44: 413664 | M44: =MONTH(G44) -> 9 | N44: mop pel, kain lap, sikat gagang.pdf | O44: Approved | Q44: 29730
B45: Shopee | C45: Pembelian Pesanan (PKM Kelapa Dua) pembersih kaca | E45: SP Belanja Kebersihan Puskesmas Kelapa Dua September 2025.pdf | G45: 45925 | I45: 378500 | L45: 378500 | M45: =MONTH(G45) -> 9 | N45: Pembersih Kaca | O45: Approved | Q45: 2852468 | S45: 980000 | T45: =S45*25 -> 24500000
B46: Shopee | C46: Pembelian Pesanan (PKM Kelapa Dua) hand sanitizer | E46: SP Belanja Kebersihan Puskesmas Kelapa Dua September 2025.pdf | G46: 45925 | I46: 436963 | L46: 436963 | M46: =MONTH(G46) -> 9 | N46: hand sanitizer | O46: Approved | Q46: =sum(Q43:Q45) -> 4593910
B47: Shopee | C47: Pembelian Pesanan (PKM Kelapa Dua) karbol, cuci tangan, cuci piring | E47: SP Belanja Kebersihan Puskesmas Kelapa Dua September 2025.pdf | G47: 45925 | I47: 565800 | L47: 565800 | M47: =MONTH(G47) -> 9 | N47: karbol,cucitangan,cucipiring | O47: Approved | Q47: =Q46-I43 -> 218910
B48: Shopee | C48: Pembelian Pesanan (PKM Kelapa Dua) byclin | E48: SP Belanja Kebersihan Puskesmas Kelapa Dua September 2025.pdf | G48: 45925 | I48: 509557 | L48: 509557 | M48: =MONTH(G48) -> 9 | N48: byclin | O48: Approved
B49: Shopee | C49: Pembelian Pesanan (PKM Kelapa Dua) porstex | E49: SP Belanja Kebersihan Puskesmas Kelapa Dua September 2025.pdf | G49: 45925 | I49: 710160 | L49: 710160 | M49: =MONTH(G49) -> 9 | N49: porstex | O49: Approved | R49: Nama Barang | S49: Satuan/volume | T49: Banyaknya | U49: Sales | V49: PPN | W49: beli | X49: Harga | Y49: PPN
B50: Shopee | C50: Pembelian Pesanan (PKM Bojong Gede) Spons Sapu Lidi Sapu lantai kain pel | E50: surat-pesanan-EP-01K64RKYR001N8JKV3440C0J3N Pkm Bojong Gede (1).pdf | G50: 45930 | I50: 356981 | L50: 356981 | M50: =MONTH(G50) -> 9 | N50: Pembelanjaan PKM Bojong Gede (Spons^J Sapu Lidi^J Sapu lantai^J Pel).pdf | O50: Approved | R50: egens | S50: 25 pack | T50: 5 | U50: 1900000 | V50: =U50*11% -> 209000 | W50: 125 | X50: 4375000 | Y50: =X50*11% -> 481250 | Z50: =T50*U50 -> 9500000 | AA50: =Z50-X50 -> 5125000
B51: Shopee | C51: Pembelian Pesanan (PKM Bojong Gede) Karbol dan Sabun cuci tangan | E51: surat-pesanan-EP-01K64RKYR001N8JKV3440C0J3N Pkm Bojong Gede (1).pdf | G51: 45930 | I51: 1255860 | L51: 1255860 | M51: =MONTH(G51) -> 9 | N51: Pembelanjaan PKM Bojong Gede (Karbol dan Sabun Cuci Tangan).pdf | O51: Approved | R51: safety box | S51: 5L | T51: 10 | U51: 33000 | V51: =U51*11% -> 3630
B52: Shopee | C52: Pembelian Pesanan (PKM Bojong Gede) Tissue | E52: surat-pesanan-EP-01K64RKYR001N8JKV3440C0J3N Pkm Bojong Gede (1).pdf | G52: 45930 | I52: 912900 | L52: 912900 | M52: =MONTH(G52) -> 9 | N52: Pembelian Pesanan PKM Bojong Gede (Tissue) | O52: Approved | R52: bimaxima | S52: 4x5ml | T52: 1 | U52: 3166240 | V52: =U52*11% -> 348286.4
B53: PT. Bintang Setya Media | C53: Pembayaran Service Printer | G53: 45919 | I53: 780000 | L53: 780000 | M53: =MONTH(G53) -> 9 | N53: Service Printer | O53: Approved | R53: SALES | U53: =sum(U50:U52) -> 5099240 | W53: =U53-V52 -> 4750953.6
B54: PT. Bintang Setya Media | C54: Pembelian Tinta Printer | G54: 45919 | I54: 500000 | L54: 500000 | M54: =MONTH(G54) -> 9 | N54: Pembelian Tinta Printer | O54: Approved
B55: PT. Top Point Medical | C55: Pembelian Pesanan RS Suyoto | E55: Pesanan RS Suyoto | F55: PO ke TP (Pesanan RS Suyoto) | G55: 45911 | I55: 2760901 | J55: 303699 | L55: =I55+J55 -> 3064600 | M55: =MONTH(G55) -> 9 | N55: inv TP (RS Suyoto) | O55: Approved | P55: FP - Top Point (RS Suyoto)
B56: PT. Whira Pitoe Usaha Bersama | C56: Pembelian Biomaxima Biopath (Dinkes Tasikmalaya) | E56: SP 46 Genta (1).pdf | G56: 45926 | I56: 1831351 | J56: 201449 | L56: =I56+J56 -> 2032800 | M56: =MONTH(G56) -> 9 | N56: Pembelian Barang ke PT.Whira
B57: PT. Sangiang Karya Mandiri | C57: Pembelian Egens Combo Diagnostic Kit Multi Drug Panel (Dinkes Tasikmalaya) | E57: SP 46 Genta (1).pdf | G57: 45925 | I57: 4375000 | J57: 481250 | L57: =I57+J57 -> 4856250 | M57: =MONTH(G57) -> 9 | N57: Pembelian ke PT. Sangiang
B58: PT. BSM | C58: Pembelian Monetes | E58: SP 46 Genta (1).pdf | G58: 45925 | I58: 567572 | J58: 62433 | L58: =I58+J58 -> 630005 | M58: =MONTH(G58) -> 9 | N58: Pembelian Pesanan Dinkes Tasik (PT BSM)
B60: Pramuka | C60: Pembelian 70 Box sarung tangan (Pesanan PKM Sentul) | E60: BMHP Sentul.pdf | G60: 45937 | I60: 2800000 | L60: 2800000 | M60: =MONTH(G60) -> 10 | N60: Sarung Tangan Latex
B61: Shopee | C61: Alcohol Swab (PKM SENTUL) 50 Box | E61: BMHP Sentul.pdf | G61: 45937 | I61: 394000 | L61: 394000 | M61: =MONTH(G61) -> 10 | N61: Alcohol swab
B62: Shopee | C62: Masker 50 Box (PKM Sentul) | E62: BMHP Sentul.pdf | G62: 45937 | I62: 527800 | L62: 527800 | M62: =MONTH(G62) -> 10 | N62: Masker Baymed Hijab
B63: Top Point | C63: Pembelian Spuit 3cc | E63: BMHP Sentul.pdf | F63: MPG-021025003 - Top Point (PKM Sentul).pdf | G63: 45936 | I63: 1091992 | J63: 120119 | K63: tempo | L63: =I63+J63 -> 1212111 | M63: =MONTH(G63) -> 10 | N63: INV TP (6 okt 2025).pdf | P63: FP TP (6 okt 2025).pdf
B64: BSM | C64: Pembelian Tabung Plan Merah, Stik Asam Urat, Stik Kolestrol, EDTA 3ML (PKM CIAWI) | E64: surat-pesanan-EP-01K6M1B6X4Q02429HWGQBC58JY PKM CIAWI.pdf | F64: MPG-031025005 - PT. BSM ...pdf | G64: 45937 | I64: 7005554 | L64: 7005554 | M64: =MONTH(G64) -> 10 | N64: INV BSM 7/10/25 | O64: Approved
B65: shopee | C65: Pembelian Yellow Tip (PKM CIAWI) | E65: surat-pesanan-EP-01K6M1B6X4Q02429HWGQBC58JY PKM CIAWI.pdf | G65: 45937 | I65: 79108 | L65: 79108 | M65: =MONTH(G65) -> 10 | N65: yellow tip pkm ciawi | O65: Approved
B66: shopee | C66: Pembelian Kartu Goldar (PKM CIAWI) | E66: surat-pesanan-EP-01K6M1B6X4Q02429HWGQBC58JY PKM CIAWI.pdf | G66: 45937 | I66: 66990 | L66: 66990 | M66: =MONTH(G66) -> 10 | N66: Kartu Goldar PKM ciawi | O66: Approved
B67: shopee | C67: Pembelian Pot Urine (PKM CIAWI) | E67: surat-pesanan-EP-01K6M1B6X4Q02429HWGQBC58JY PKM CIAWI.pdf | G67: 45937 | I67: 476400 | L67: 476400 | M67: =MONTH(G67) -> 10 | N67: Pot urine pkm ciawi | O67: Approved
C68: Cashback pkm cihideng udik2, cogrek,cangkurawok | G68: 45937 | I68: 1788970.3 | L68: 1788970.3 | M68: =MONTH(G68) -> 10 | O68: Approved
B69: PT. Wira Pithoe | C69: Pembelian Reagen Cholestrol (Dinkes Tasik) | E69: SP Dinkes Tasikmalaya | G69: 45940 | I69: 840000 | J69: 92400 | L69: =I69+J69 -> 932400 | M69: =MONTH(G69) -> 10 | N69: INV - PT. WHIRA | O69: Approved
B70: PT. BSM | C70: Pembelian Edta (Dinkes Tasik) dan untuk stock | E70: SP Dinkes Tasikmalaya | F70: PO - BSM (dinkes tasik).pdf | G70: 45938 | I70: 306304 | J70: 33693 | L70: =I70+J70 -> 339997 | M70: =MONTH(G70) -> 10 | N70: Inv BSM - 8/10/25 | O70: Approved
B71: Shopee | C71: Cover glass (Dinkes Tasik) | E71: SP Dinkes Tasikmalaya | G71: 45938 | I71: 21500 | L71: 21500 | M71: =MONTH(G71) -> 10 | N71: cover glass (dinkes tasik).pdf | O71: Approved
B72: PT. Biosensor | C72: Pembelian Stik Codefree (PKM CIAWI) | E72: surat-pesanan-EP-01K6M1B6X4Q02429HWGQBC58JY PKM CIAWI.pdf | F72: MPG-031025004 - PO BIOSENSOR.pdf | G72: 45940 | I72: 1340090 | J72: 147409 | L72: =I72+J72 -> 1487499 | M72: =MONTH(G72) -> 10 | N72: 4356 - INV BIOSENSOR.pdf | O72: Approved
C73: Cashback PKM Kelapa 2 | E73: SP Belanja Kebersihan Puskesmas Kelapa Dua September 2025.pdf | G73: 45938 | I73: 1451916 | L73: 1451916 | M73: =MONTH(G73) -> 10 | N73: cashback pkm kelapa 2.pdf | O73: Approved
B74: PT. Klipindo Plastik Pratama | C74: Pesanan Plastik (RSUD Ps.Minggu) 1.000 Pack dan pkm sentul 300 pack | E74: Rsud Pasar Minggu.pdf | F74: MPG-101025010 - PT. Klipindo Plastik Pratama.pdf | G74: 45940 | I74: 11525900 | L74: 11525900 | M74: =MONTH(G74) -> 10 | N74: Plastik Klip.pdf | O74: Approved
B75: Shopee | C75: Pembelian Pesanan APAR 3.5 KG (PKM Bojong) | E75: surat-pesanan-EP-01K6M7R46NK0HCYZ9GCCRKJKVV Pkm Bojong.pdf | G75: 45940 | I75: 876000 | L75: 876000 | M75: =MONTH(G75) -> 10 | N75: apar 3,5 kg.pdf | O75: Approved
B76: PT. Top Point | C76: Pembelian Feeding Tube (RSUD DR. ADJIDARMO) | E76: SP RSUD Adjidarmo.pdf | F76: MPG-081025007 - Top Point (Feeding Tube).pdf | H76: Tempo | I76: 5929000 | L76: 5929000 | M76: =MONTH(G76) -> 12 | O76: Approved | P76: dibyr pake bank apa?
B77: PT Wira Pithoe | C77: Pesanan Dinkes Tasik (koletsrol,trigiliserida,sgot,sgpt,ureum,kreatinin) | E77: Surat Pesanan Dinkes Tasikmalaya | F77: MPG-131025012 - PT WIRA PITHOE (dinkes tasik).pdf | G77: 45943 | I77: 10074000 | J77: 1108140 | L77: =I77+J77 -> 11182140 | M77: =MONTH(G77) -> 10 | N77: WPUB3523 PT MATA PENSIL GLOBALINDO (1).pdf | O77: Approved
B78: PT. Dhyas Mitra Usaha | C78: Pesanan Dinkes Tasik (Pot urine, Alcohol swab, sarung tangan s/m) | E78: Surat Pesanan Dinkes Tasikmalaya | F78: MPG-131025013 - PT. DHYAS (Dinkes Tasikmalaya).pdf | G78: 45943 | I78: 1994600 | L78: =I78 -> 1994600 | M78: =MONTH(G78) -> 10 | N78: 024_ INV PT MATA PENSIL GLOBALINDO.pdf | O78: Approved
B79: PT. SGM | C79: Pesanan Dinkes Tasik (Goldar Set) | E79: Surat Pesanan Dinkes Tasikmalaya | F79: MPG-131025015 - PT.SGM.pdf | G79: 45943 | I79: 652000 | J79: 71720 | L79: =I79+J79 -> 723720 | M79: =MONTH(G79) -> 10 | N79: inv SGM (dinkes tasik) | O79: Approved
B80: PT. BSM | C80: Pesanan Dinkes Tasik (Tes kehamilan,tabung edta,tabung gel,yellow white tip,urine p,led) | E80: Surat Pesanan Dinkes Tasikmalaya | F80: MPG-131025014 -BSM (Dinkes Tasik).pdf | G80: 45943 | I80: 5634862 | J80: 619835 | L80: =I80+J80 -> 6254697 | M80: =MONTH(G80) -> 10 | N80: Inv BSM (Pesanan Dinkes) | O80: Approved
B81: shopee | C81: Pesanan Dinkes Tasik (Kartu Goldar) | E81: Surat Pesanan Dinkes Tasikmalaya | G81: 45943 | I81: 80500 | L81: =I81 -> 80500 | M81: =MONTH(G81) -> 10 | N81: Kartu Golongan Darah (Dinkes Tasik) | O81: Approved
B82: shopee | C82: Pesanan Dinkes Tasik (Rak Tabung) | E82: Surat Pesanan Dinkes Tasikmalaya | G82: 45943 | I82: 676420 | L82: 676420 | M82: =MONTH(G82) -> 10 | N82: Rak Tabung ESR | O82: Approved
B83: shopee | C83: Pesanan Dinkes Tasik ( Tourniquet) | E83: Surat Pesanan Dinkes Tasikmalaya | G83: 45943 | I83: 32070 | L83: 32070 | M83: =MONTH(G83) -> 10 | N83: Tourniquet (Dinkes Tasik) | O83: Approved
B84: shopee | C84: Pesanan Dinkes Tasik (Okplast) | E84: Surat Pesanan Dinkes Tasikmalaya | G84: 45943 | I84: 218500 | L84: 218500 | M84: =MONTH(G84) -> 10 | N84: Okplast (Dinkes Tasik) | O84: Approved
B85: shopee | C85: Pesanan Dinkes Tasik (Masker) | E85: Surat Pesanan Dinkes Tasikmalaya | G85: 45943 | I85: 81940 | L85: 81940 | M85: =MONTH(G85) -> 10 | N85: Masker (Dinkes Tasik) | O85: Approved
B86: PT.Top Point | C86: Pesanan RSPP | E86: po rspp (6) | F86: MPG-011025001 - TOP POINT (Pesanan RSPP) ..pdf | G86: 45931 | H86: tempo | I86: 3800676 | J86: 418074 | L86: =I86+J86 -> 4218750 | M86: =MONTH(G86) -> 10 | N86: Inv TP (Po 6 RSPP).pdf | O86: Approved | P86: FP - TP (po 6 rspp).pdf
B87: PT. Tirta Investama | C87: Galon Kantor (Pemakaian September) | I87: 679999 | L87: 679999 | M87: =MONTH(G87) -> 12 | N87: Galon Kantor (pemakaian september).pdf | O87: Approved | P87: FP Galon Sept.pdf
B88: PT. BSM | C88: Pesanan Tambahan (Dinkes Tasik) Safety Box | E88: SP 53 mata pensil susulan add.jpg | F88: MPG-141025016 - PT. BSM (Safety Box).pdf | G88: 45944 | I88: 612640 | J88: 67390 | L88: =I88+J88 -> 680030 | M88: =MONTH(G88) -> 10 | N88: Invoice BSM (Safety Box) | O88: Approved
B89: PT Bintang Setya Media | C89: Pembelian Tinta Printer | G89: 45939 | I89: 1000000 | L89: 1000000 | M89: =MONTH(G89) -> 10 | N89: Tinta Printer (9-oct-25).pdf | O89: Approved
B90: PT Bintang Setya Media | C90: Pembelian Tinta Printer | G90: 45943 | I90: 360000 | L90: 360000 | M90: =MONTH(G90) -> 10 | N90: Tinta Printer (13-oct-25).pdf | O90: Approved
B91: PT. BSM | C91: Pembelian Deckglass (Dinkes Tasik) | E91: SP Dinkes Tasikmalaya | F91: MPG-141025017 - PT BSM (deckglass).pdf | G91: 45944 | I91: 720721 | J91: 79279 | L91: =I91+J91 -> 800000 | M91: =MONTH(G91) -> 10 | N91: Deckglass | O91: Approved
C92: Listrik dan Parkir Gedung | G92: 45945 | I92: 5710589 | L92: 5710589 | M92: =MONTH(G92) -> 10 | N92: tagihan listrik (pemakaian sept).pdf | O92: Approved
C93: Pengajuan dinas tasik pa agus | G93: 45945 | I93: 1000000 | L93: 1000000 | M93: =MONTH(G93) -> 10 | N93: pengajuan dinas tasik.pdf | O93: Approved
C94: Pembayaran CDAKB | G94: 45945 | I94: 3000000 | L94: 3000000 | M94: =MONTH(G94) -> 10 | N94: TRIDIA_SPB-DK-251423548NOJhF0707 (2).pdf | O94: Approved
B95: PT. Top Point | C95: Pemesanan PO Ke 8 (RSPP) | E95: sp rspp (po 8) | F95: MPG-131025011 - Top Point (RSPP).pdf | G95: 45940 | H95: tempo | I95: 4560810.8 | J95: =I95*11% -> 501689.19 | L95: 5062500 | M95: =MONTH(G95) -> 10 | N95: tempo | O95: Approved
B96: PT. Top Point | C96: Stock suntikan rspp | E96: RSPP - (PO KE 9) | F96: MPG-141025019 - Top Point (Stock RSPP).pdf | G96: 45946 | H96: tempo | I96: 6081081 | J96: 668919 | L96: =I96+J96 -> 6750000 | M96: =MONTH(G96) -> 10 | N96: Invoice Top Point.pdf | O96: Approved | P96: FP --Top Point.pdf | Q96: 45985
C97: Lalamove antar barang pesanan rs adjidarmo | G97: 45946 | I97: 300000 | L97: 300000 | M97: =MONTH(G97) -> 10 | N97: Lalamove antar pesanan rs adjidarmo.pdf | O97: Approved
C98: Advance rizky bertemu kepala pkm pasir angin | G98: 45946 | I98: 500000 | L98: 500000 | M98: =MONTH(G98) -> 10 | N98: pengajuan advance kibo.pdf | O98: Approved
C99: Pembelian pesanan (UPK KEMENKES) | E99: surat-pesanan-EP-01K7DPKYXJ1AF4X8HQ0MZ3N8DV UPK KEMENKES.pdf | G99: 45947 | I99: 328500 | L99: 328500 | M99: =MONTH(G99) -> 10 | N99: Oral Gel (Pesanan UPK Kemenkes).pdf | O99: Approved
B100: PT. MBC | C100: Pembelian ganti barang rusak (pkm balekambang) | E100: Pesanan Balekambang | G100: 16-Okt-25 | I100: 536250 | J100: 58988 | L100: =I100+J100 -> 595238 | M100: =MONTH(G100) -> 10 | N100: MBC (kontrol hema).pdf | O100: Approved | P100: FP MBC.pdf
C101: Reimburse Kibo (17 okt 25) | G101: 17-okt-25 | I101: 563000 | L101: 563000 | M101: =MONTH(G101) -> 10 | N101: reimburse pengiriman barang Rizky.pdf | O101: Approved
...

Sheet APOutstanding
B1: OTOMATIS DARI SHEET PURCHASE | U1: Lampirkan BUKTI BAYAR
I2: Amount | M2: Payment | R2: A/P | S2: Remark | T2: Remark | U2: Link
A3: Code | B3: Suppliers | C3: Item | D3: Date | E3: Sales Order | F3: PO No. | G3: Date PO | H3: Invoice | I3: Rp | J3: VAT | K3: PPH 23 | L3: A/P | M3: Date | N3: By | O3: Rp | P3: Date | Q3: Other | R3: Outstanding | U3: Document
A4: =PURCHASES!A4 | B4: =IFERROR(__xludf.DUMMYFUNCTION("QUERY(PURCHASES!B4:L253)"),"Tokopedia") -> Tokopedia | C4: =IFERROR(__xludf.DUMMYFUNCTION("""COMPUTED_VALUE"""),"Pembelian Termometer PKM Balekambang") -> Pembelian Termometer PKM Balekambang | G4: =IFERROR(__xludf.DUMMYFUNCTION("""COMPUTED_VALUE"""),45816.0) -> 45816 | I4: =IFERROR(__xludf.DUMMYFUNCTION("""COMPUTED_VALUE"""),705700.0) -> 705700 | L4: =IFERROR(__xludf.DUMMYFUNCTION("""COMPUTED_VALUE"""),705700.0) -> 705700 | M4: 11-agustus-25 | N4: BCA MPG | O4: 705700 | P4: 11-agus-25 | R4: =L4-O4 -> 0 | S4: =IF(#REF!>0,"ost","-") -> #REF! | T4: - | U4: Pembelian Termometer PKM
B5: =IFERROR(__xludf.DUMMYFUNCTION("""COMPUTED_VALUE"""),"Shopee") -> Shopee | C5: =IFERROR(__xludf.DUMMYFUNCTION("""COMPUTED_VALUE"""),"Pembelian Kursi, Meja dan Lemari PKM Gandoang ") -> Pembelian Kursi, Meja dan Lemari PKM Gandoang | G5: =IFERROR(__xludf.DUMMYFUNCTION("""COMPUTED_VALUE"""),45882.0) -> 45882 | I5: =IFERROR(__xludf.DUMMYFUNCTION("""COMPUTED_VALUE"""),1.13816E7) -> 11381600 | L5: =IFERROR(__xludf.DUMMYFUNCTION("""COMPUTED_VALUE"""),1.13816E7) -> 11381600 | M5: 11-agustus-25 | N5: BCA MPG | O5: 11381600 | P5: 11-agustus-25 | R5: =L5-O5 -> 0 | S5: =IF(R5>0,"ost","-") -> - | T5: - | U5: Pembelian Pesanan PKM Gandoang.pdf
A6: =PURCHASES!A6 | B6: =IFERROR(__xludf.DUMMYFUNCTION("""COMPUTED_VALUE"""),"Shopee") -> Shopee | C6: =IFERROR(__xludf.DUMMYFUNCTION("""COMPUTED_VALUE"""),"Pembelian Composit Resin, Umblical, Bonding, Gludaten, Bisturi PKM DPT Saketi") -> Pembelian Composit Resin, Umblical, Bonding, Gludaten, Bisturi PKM DPT Saketi | E6: =IFERROR(__xludf.DUMMYFUNCTION("""COMPUTED_VALUE"""),"SURAT PESANAN PKM DPT SAKETI.jpeg") -> SURAT PESANAN PKM DPT SAKETI.jpeg | G6: =IFERROR(__xludf.DUMMYFUNCTION("""COMPUTED_VALUE"""),45882.0) -> 45882 | I6: =IFERROR(__xludf.DUMMYFUNCTION("""COMPUTED_VALUE"""),2654410.0) -> 2654410 | L6: =IFERROR(__xludf.DUMMYFUNCTION("""COMPUTED_VALUE"""),2654410.0) -> 2654410 | M6: 11-agustus-25 | N6: BCA MPG | O6: 2654410 | P6: 11-agustus-25 | R6: =L6-O6 -> 0 | S6: =IF(R6>0,"ost","-") -> - | T6: - | U6: Bukti TF Pesanan PKM DPT Saketi.pdf
A7: =PURCHASES!A7 | B7: =IFERROR(__xludf.DUMMYFUNCTION("""COMPUTED_VALUE"""),"PT. Top Point Medical") -> PT. Top Point Medical | C7: =IFERROR(__xludf.DUMMYFUNCTION("""COMPUTED_VALUE"""),"TP Infusion Set Advance") -> TP Infusion Set Advance | E7: =IFERROR(__xludf.DUMMYFUNCTION("""COMPUTED_VALUE"""),"Surat Pesanan RSPP") -> Surat Pesanan RSPP | F7: =IFERROR(__xludf.DUMMYFUNCTION("""COMPUTED_VALUE"""),"PO Infusion Set - Top Point") -> PO Infusion Set - Top Point | G7: =IFERROR(__xludf.DUMMYFUNCTION("""COMPUTED_VALUE"""),45880.0) -> 45880 | I7: =IFERROR(__xludf.DUMMYFUNCTION("""COMPUTED_VALUE"""),3040541.0) -> 3040541 | J7: =IFERROR(__xludf.DUMMYFUNCTION("""COMPUTED_VALUE"""),334459.51) -> 334459.51 | L7: =IFERROR(__xludf.DUMMYFUNCTION("""COMPUTED_VALUE"""),3375000.51) -> 3375000.5 | M7: 11-agustus-25 | N7: BCA MPG | O7: 3375000 | P7: 11-agustus-25 | R7: =L7-O7 -> 0.51 | S7: =IF(R7>0,"ost","-") -> ost | T7: - | U7: Pembayaran ke Top Point
A8: =PURCHASES!A8 | B8: =IFERROR(__xludf.DUMMYFUNCTION("""COMPUTED_VALUE"""),"Shopee") -> Shopee | C8: =IFERROR(__xludf.DUMMYFUNCTION("""COMPUTED_VALUE"""),"Pembelian Gludenta DPT Saketi") -> Pembelian Gludenta DPT Saketi | E8: =IFERROR(__xludf.DUMMYFUNCTION("""COMPUTED_VALUE"""),"part of SO no.3") -> part of SO no.3 | G8: =IFERROR(__xludf.DUMMYFUNCTION("""COMPUTED_VALUE"""),45882.0) -> 45882 | I8: =IFERROR(__xludf.DUMMYFUNCTION("""COMPUTED_VALUE"""),1408256.0) -> 1408256 | L8: =IFERROR(__xludf.DUMMYFUNCTION("""COMPUTED_VALUE"""),1408256.0) -> 1408256 | M8: 11-agustus-25 | N8: BCA MPG | O8: 1408256 | P8: 11-agustus-25 | R8: =L8-O8 -> 0 | S8: =IF(R8>0,"ost","-") -> - | T8: - | U8: Bukti Bayar Gludenta
B9: =IFERROR(__xludf.DUMMYFUNCTION("""COMPUTED_VALUE"""),"Top Point") -> Top Point | C9: =IFERROR(__xludf.DUMMYFUNCTION("""COMPUTED_VALUE"""),"Pembelian Suntikan DPT Saketi") -> Pembelian Suntikan DPT Saketi | E9: =IFERROR(__xludf.DUMMYFUNCTION("""COMPUTED_VALUE"""),"part of SO no.3") -> part of SO no.3 | G9: =IFERROR(__xludf.DUMMYFUNCTION("""COMPUTED_VALUE"""),45888.0) -> 45888 | I9: =IFERROR(__xludf.DUMMYFUNCTION("""COMPUTED_VALUE"""),136554.0) -> 136554 | J9: =IFERROR(__xludf.DUMMYFUNCTION("""COMPUTED_VALUE"""),15020.94) -> 15020.94 | L9: =IFERROR(__xludf.DUMMYFUNCTION("""COMPUTED_VALUE"""),151574.94) -> 151574.94 | M9: 11-agustus-25 | N9: BCA MPG | O9: 151575 | P9: 11-agustus-25 | R9: =L9-O9 -> -0.06 | S9: =IF(R9>0,"ost","-") -> - | T9: - | U9: Bukti Bayar Top Point
B10: =IFERROR(__xludf.DUMMYFUNCTION("""COMPUTED_VALUE"""),"Sarana Megamedilab Sejahtera (SMS)") -> Sarana Megamedilab Sejahtera (SMS) | C10: =IFERROR(__xludf.DUMMYFUNCTION("""COMPUTED_VALUE"""),"Pembelian Lampu ") -> Pembelian Lampu | E10: =IFERROR(__xludf.DUMMYFUNCTION("""COMPUTED_VALUE"""),"RSUD Cibinong") -> RSUD Cibinong | G10: =IFERROR(__xludf.DUMMYFUNCTION("""COMPUTED_VALUE"""),45869.0) -> 45869 | I10: =IFERROR(__xludf.DUMMYFUNCTION("""COMPUTED_VALUE"""),2800000.0) -> 2800000 | J10: =IFERROR(__xludf.DUMMYFUNCTION("""COMPUTED_VALUE"""),308000.0) -> 308000 | L10: =IFERROR(__xludf.DUMMYFUNCTION("""COMPUTED_VALUE"""),3108000.0) -> 3108000 | M10: 11-agustus-25 | N10: BCA MPG | O10: 3108000 | P10: 11-agustus-25 | R10: =L10-O10 -> 0 | S10: =IF(R10>0,"ost","-") -> - | T10: -
B11: =IFERROR(__xludf.DUMMYFUNCTION("""COMPUTED_VALUE"""),"Shopee") -> Shopee | C11: =IFERROR(__xludf.DUMMYFUNCTION("""COMPUTED_VALUE"""),"Pembelian Pesanan Plastik (PKM Cimandala)") -> Pembelian Pesanan Plastik (PKM Cimandala) | E11: =IFERROR(__xludf.DUMMYFUNCTION("""COMPUTED_VALUE"""),"-Menyusul-") -> -Menyusul- | G11: =IFERROR(__xludf.DUMMYFUNCTION("""COMPUTED_VALUE"""),45895.0) -> 45895 | I11: =IFERROR(__xludf.DUMMYFUNCTION("""COMPUTED_VALUE"""),2021100.0) -> 2021100 | L11: =IFERROR(__xludf.DUMMYFUNCTION("""COMPUTED_VALUE"""),2021100.0) -> 2021100 | M11: 11-agustus-25 | N11: BCA MPG | O11: 2021100 | P11: 11-agustus-25 | R11: =L11-O11 -> 0 | S11: =IF(R11>0,"ost","-") -> - | T11: -
B12: =IFERROR(__xludf.DUMMYFUNCTION("""COMPUTED_VALUE"""),"Shopee") -> Shopee | C12: =IFERROR(__xludf.DUMMYFUNCTION("""COMPUTED_VALUE"""),"Pembelian Yellow dan Blue Tip (PKM Cangkurawok)") -> Pembelian Yellow dan Blue Tip (PKM Cangkurawok) | E12: =IFERROR(__xludf.DUMMYFUNCTION("""COMPUTED_VALUE"""),"surat-pesanan-EP-01K387EQ0896Y44BX6R9RSJ2FA (Pkm Cangkurawok)") -> surat-pesanan-EP-01K387EQ0896Y44BX6R9RSJ2FA (Pkm Cangkurawok) | G12: =IFERROR(__xludf.DUMMYFUNCTION("""COMPUTED_VALUE"""),45895.0) -> 45895 | I12: =IFERROR(__xludf.DUMMYFUNCTION("""COMPUTED_VALUE"""),82499.0) -> 82499 | L12: =IFERROR(__xludf.DUMMYFUNCTION("""COMPUTED_VALUE"""),82499.0) -> 82499 | M12: 11-agustus-25 | N12: BCA MPG | O12: 82499 | P12: 11-agustus-25 | R12: =L12-O12 -> 0 | S12: =IF(R12>0,"ost","-") -> - | T12: -
B13: =IFERROR(__xludf.DUMMYFUNCTION("""COMPUTED_VALUE"""),"Shopee") -> Shopee | C13: =IFERROR(__xludf.DUMMYFUNCTION("""COMPUTED_VALUE"""),"Pembelanjaan Pesanan (PKM Pasir Angin)") -> Pembelanjaan Pesanan (PKM Pasir Angin) | E13: =IFERROR(__xludf.DUMMYFUNCTION("""COMPUTED_VALUE"""),"surat-pesanan-EP-01K381B70E6329EG57Q86XG5DH.pdf (PKM Pasir angin) 27-08-25") -> surat-pesanan-EP-01K381B70E6329EG57Q86XG5DH.pdf (PKM Pasir angin) 27-08-25 | G13: =IFERROR(__xludf.DUMMYFUNCTION("""COMPUTED_VALUE"""),45896.0) -> 45896 | I13: =IFERROR(__xludf.DUMMYFUNCTION("""COMPUTED_VALUE"""),1086000.0) -> 1086000 | L13: =IFERROR(__xludf.DUMMYFUNCTION("""COMPUTED_VALUE"""),1086000.0) -> 1086000 | M13: 11-agustus-25 | N13: BCA MPG | O13: 1086000 | P13: 11-agustus-25 | R13: =L13-O13 -> 0 | S13: =IF(R13>0,"ost","-") -> - | T13: -
B14: =IFERROR(__xludf.DUMMYFUNCTION("""COMPUTED_VALUE"""),"Top Point") -> Top Point | C14: =IFERROR(__xludf.DUMMYFUNCTION("""COMPUTED_VALUE"""),"Pembelian TP Infusion Set Advance (RSPP)") -> Pembelian TP Infusion Set Advance (RSPP) | E14: =IFERROR(__xludf.DUMMYFUNCTION("""COMPUTED_VALUE"""),"Surat Pesanan RSPP PO 2 (20-08-25)") -> Surat Pesanan RSPP PO 2 (20-08-25) | F14: =IFERROR(__xludf.DUMMYFUNCTION("""COMPUTED_VALUE"""),"PO ke Top Point (20-08-25)") -> PO ke Top Point (20-08-25) | G14: =IFERROR(__xludf.DUMMYFUNCTION("""COMPUTED_VALUE"""),45890.0) -> 45890 | I14: =IFERROR(__xludf.DUMMYFUNCTION("""COMPUTED_VALUE"""),3040541.0) -> 3040541 | J14: =IFERROR(__xludf.DUMMYFUNCTION("""COMPUTED_VALUE"""),334459.0) -> 334459 | L14: =IFERROR(__xludf.DUMMYFUNCTION("""COMPUTED_VALUE"""),3375000.0) -> 3375000 | M14: 11-agustus-25 | N14: BCA MPG | O14: 3375000 | P14: 11-agustus-25 | R14: =L14-O14 -> 0 | S14: =IF(R14>0,"ost","-") -> - | T14: -
B15: =IFERROR(__xludf.DUMMYFUNCTION("""COMPUTED_VALUE"""),"PT Demaz Noer Abadi") -> PT Demaz Noer Abadi | C15: =IFERROR(__xludf.DUMMYFUNCTION("""COMPUTED_VALUE"""),"Pembelian Pesanan (PKM Karyamekar) Test Strip") -> Pembelian Pesanan (PKM Karyamekar) Test Strip | E15: =IFERROR(__xludf.DUMMYFUNCTION("""COMPUTED_VALUE"""),"Pesanan PKM Karya Mekar (28-08-25)") -> Pesanan PKM Karya Mekar (28-08-25) | F15: =IFERROR(__xludf.DUMMYFUNCTION("""COMPUTED_VALUE"""),"PO MPG-270825008 Biosensor.pdf") -> PO MPG-270825008 Biosensor.pdf | G15: =IFERROR(__xludf.DUMMYFUNCTION("""COMPUTED_VALUE"""),45897.0) -> 45897 | I15: =IFERROR(__xludf.DUMMYFUNCTION("""COMPUTED_VALUE"""),700000.0) -> 700000 | J15: =IFERROR(__xludf.DUMMYFUNCTION("""COMPUTED_VALUE"""),77000.0) -> 77000 | L15: =IFERROR(__xludf.DUMMYFUNCTION("""COMPUTED_VALUE"""),777000.0) -> 777000 | M15: 11-agustus-25 | N15: BCA MPG | O15: 777000 | P15: 11-agustus-25 | R15: =L15-O15 -> 0 | S15: =IF(R15>0,"ost","-") -> - | T15: -
B16: =IFERROR(__xludf.DUMMYFUNCTION("""COMPUTED_VALUE"""),"PT. Elba Lab Medika") -> PT. Elba Lab Medika | C16: =IFERROR(__xludf.DUMMYFUNCTION("""COMPUTED_VALUE"""),"Pembelian Pesanan (PKM Ciawi ) Uric acid dan Glucose") -> Pembelian Pesanan (PKM Ciawi ) Uric acid dan Glucose | E16: =IFERROR(__xludf.DUMMYFUNCTION("""COMPUTED_VALUE"""),"surat-pesanan-EP-01K3Q5WHEXQ3VZNQBKWARSAMDH Pkm Ciawi Erba.pdf") -> surat-pesanan-EP-01K3Q5WHEXQ3VZNQBKWARSAMDH Pkm Ciawi Erba.pdf | F16: =IFERROR(__xludf.DUMMYFUNCTION("""COMPUTED_VALUE"""),"PO MPG-270825006 Elba Medika Revisi.pdf") -> PO MPG-270825006 Elba Medika Revisi.pdf | G16: =IFERROR(__xludf.DUMMYFUNCTION("""COMPUTED_VALUE"""),45896.0) -> 45896 | I16: =IFERROR(__xludf.DUMMYFUNCTION("""COMPUTED_VALUE"""),6088810.0) -> 6088810 | J16: =IFERROR(__xludf.DUMMYFUNCTION("""COMPUTED_VALUE"""),669769.0) -> 669769 | L16: =IFERROR(__xludf.DUMMYFUNCTION("""COMPUTED_VALUE"""),6758579.0) -> 6758579 | M16: 11-agustus-25 | N16: BCA MPG | O16: 6758579 | P16: 11-agustus-25 | R16: =L16-O16 -> 0 | S16: =IF(R16>0,"ost","-") -> - | T16: -
B17: =IFERROR(__xludf.DUMMYFUNCTION("""COMPUTED_VALUE"""),"Shopee") -> Shopee | C17: =IFERROR(__xludf.DUMMYFUNCTION("""COMPUTED_VALUE"""),"Pembelian Pesanan (PKM Karyamekar) Alcohol swab, blue dan yellow tip") -> Pembelian Pesanan (PKM Karyamekar) Alcohol swab, blue dan yellow tip | E17: =IFERROR(__xludf.DUMMYFUNCTION("""COMPUTED_VALUE"""),"part of SO no.15") -> part of SO no.15 | G17: =IFERROR(__xludf.DUMMYFUNCTION("""COMPUTED_VALUE"""),45896.0) -> 45896 | I17: =IFERROR(__xludf.DUMMYFUNCTION("""COMPUTED_VALUE"""),206508.0) -> 206508 | L17: =IFERROR(__xludf.DUMMYFUNCTION("""COMPUTED_VALUE"""),206508.0) -> 206508 | M17: 11-agustus-25 | N17: BCA MPG | O17: 206508 | P17: 11-agustus-25 | R17: =L17-O17 -> 0 | S17: =IF(R17>0,"ost","-") -> - | T17: -
B18: =IFERROR(__xludf.DUMMYFUNCTION("""COMPUTED_VALUE"""),"Shopee ") -> Shopee | C18: =IFERROR(__xludf.DUMMYFUNCTION("""COMPUTED_VALUE"""),"Pembelian Pesanan (PKM Pasir Angin) Apar 3kg") -> Pembelian Pesanan (PKM Pasir Angin) Apar 3kg | E18: =IFERROR(__xludf.DUMMYFUNCTION("""COMPUTED_VALUE"""),"surat-pesanan-EP-01K3T38R3TQ03RS3GZPYQRVWJ9 PKM Pasir Angin (Apar)") -> surat-pesanan-EP-01K3T38R3TQ03RS3GZPYQRVWJ9 PKM Pasir Angin (Apar) | G18: =IFERROR(__xludf.DUMMYFUNCTION("""COMPUTED_VALUE"""),45898.0) -> 45898 | I18: =IFERROR(__xludf.DUMMYFUNCTION("""COMPUTED_VALUE"""),541000.0) -> 541000 | L18: =IFERROR(__xludf.DUMMYFUNCTION("""COMPUTED_VALUE"""),541000.0) -> 541000 | M18: 45901 | N18: BCA MPG | O18: 541000 | P18: 45901 | R18: =L18-O18 -> 0 | S18: =IF(R18>0,"ost","-") -> - | T18: -
B19: =IFERROR(__xludf.DUMMYFUNCTION("""COMPUTED_VALUE"""),"PT. Burhan Sejahtera Mulia") -> PT. Burhan Sejahtera Mulia | C19: =IFERROR(__xludf.DUMMYFUNCTION("""COMPUTED_VALUE"""),"Pembelian Pesanan (PKM Karyamekar) Vacum Tube Plain") -> Pembelian Pesanan (PKM Karyamekar) Vacum Tube Plain | E19: =IFERROR(__xludf.DUMMYFUNCTION("""COMPUTED_VALUE"""),"Patt of SO np.15") -> Patt of SO np.15 | F19: =IFERROR(__xludf.DUMMYFUNCTION("""COMPUTED_VALUE"""),"PO ke PT. BSM (vacum tube)") -> PO ke PT. BSM (vacum tube) | G19: =IFERROR(__xludf.DUMMYFUNCTION("""COMPUTED_VALUE"""),45898.0) -> 45898 | I19: =IFERROR(__xludf.DUMMYFUNCTION("""COMPUTED_VALUE"""),425000.0) -> 425000 | J19: =IFERROR(__xludf.DUMMYFUNCTION("""COMPUTED_VALUE"""),46750.0) -> 46750 | L19: =IFERROR(__xludf.DUMMYFUNCTION("""COMPUTED_VALUE"""),471750.0) -> 471750 | M19: 45901 | N19: BCA MPG | O19: 471750 | P19: 45901 | R19: =L19-O19 -> 0 | S19: =IF(R19>0,"ost","-") -> - | T19: -
B20: =IFERROR(__xludf.DUMMYFUNCTION("""COMPUTED_VALUE"""),"Shopee") -> Shopee | C20: =IFERROR(__xludf.DUMMYFUNCTION("""COMPUTED_VALUE"""),"Pembelian Pesanan (PKM Bojong) cover glass dan bisturi") -> Pembelian Pesanan (PKM Bojong) cover glass dan bisturi | E20: =IFERROR(__xludf.DUMMYFUNCTION("""COMPUTED_VALUE"""),"Surat Pesanan PKM Bojong (3 Sep 2025)") -> Surat Pesanan PKM Bojong (3 Sep 2025) | G20: =IFERROR(__xludf.DUMMYFUNCTION("""COMPUTED_VALUE"""),45903.0) -> 45903 | I20: =IFERROR(__xludf.DUMMYFUNCTION("""COMPUTED_VALUE"""),96580.0) -> 96580 | L20: =IFERROR(__xludf.DUMMYFUNCTION("""COMPUTED_VALUE"""),96580.0) -> 96580 | M20: 45903 | N20: BCA MPG | O20: 96580 | P20: 45903 | R20: =L20-O20 -> 0 | S20: =IF(R20>0,"ost","-") -> - | T20: - | U20: WhatsApp Image 2025-09-03 at 17.05.49.jpeg
B21: =IFERROR(__xludf.DUMMYFUNCTION("""COMPUTED_VALUE"""),"Shopee") -> Shopee | C21: =IFERROR(__xludf.DUMMYFUNCTION("""COMPUTED_VALUE"""),"Pembelian Pesanan (PKM Bojong) kassa steril") -> Pembelian Pesanan (PKM Bojong) kassa steril | E21: =IFERROR(__xludf.DUMMYFUNCTION("""COMPUTED_VALUE"""),"Surat Pesanan PKM Bojong (3 Sep 2025)") -> Surat Pesanan PKM Bojong (3 Sep 2025) | G21: =IFERROR(__xludf.DUMMYFUNCTION("""COMPUTED_VALUE"""),45903.0) -> 45903 | I21: =IFERROR(__xludf.DUMMYFUNCTION("""COMPUTED_VALUE"""),402500.0) -> 402500 | L21: =IFERROR(__xludf.DUMMYFUNCTION("""COMPUTED_VALUE"""),402500.0) -> 402500 | M21: 45903 | N21: BCA MPG | O21: 402500 | P21: 45903 | R21: =L21-O21 -> 0 | S21: =IF(R21>0,"ost","-") -> - | T21: - | U21: WhatsApp Image 2025-09-03 at 17.04.58.jpeg
B22: =IFERROR(__xludf.DUMMYFUNCTION("""COMPUTED_VALUE"""),"Toko Pramuka") -> Toko Pramuka | C22: =IFERROR(__xludf.DUMMYFUNCTION("""COMPUTED_VALUE"""),"Pembelian Pesanan (PKM Sentul) 10box Safeguard") -> Pembelian Pesanan (PKM Sentul) 10box Safeguard | E22: =IFERROR(__xludf.DUMMYFUNCTION("""COMPUTED_VALUE"""),"-Menyusul-") -> -Menyusul- | G22: =IFERROR(__xludf.DUMMYFUNCTION("""COMPUTED_VALUE"""),45903.0) -> 45903 | I22: =IFERROR(__xludf.DUMMYFUNCTION("""COMPUTED_VALUE"""),430000.0) -> 430000 | L22: =IFERROR(__xludf.DUMMYFUNCTION("""COMPUTED_VALUE"""),430000.0) -> 430000 | M22: batal | N22: BCA MPG | R22: batal | S22: batal | T22: - | V22: gajadi pesan
B23: =IFERROR(__xludf.DUMMYFUNCTION("""COMPUTED_VALUE"""),"Top Point") -> Top Point | C23: =IFERROR(__xludf.DUMMYFUNCTION("""COMPUTED_VALUE"""),"Pembelian Pesanan (RSPP) PO ke 3 ") -> Pembelian Pesanan (RSPP) PO ke 3 | E23: =IFERROR(__xludf.DUMMYFUNCTION("""COMPUTED_VALUE"""),"Surat Pesanan RSPP (PO 3)") -> Surat Pesanan RSPP (PO 3) | F23: =IFERROR(__xludf.DUMMYFUNCTION("""COMPUTED_VALUE"""),"PO ke Top Point (Pesanan RSPP PO 3)") -> PO ke Top Point (Pesanan RSPP PO 3) | G23: =IFERROR(__xludf.DUMMYFUNCTION("""COMPUTED_VALUE"""),45896.0) -> 45896 | I23: =IFERROR(__xludf.DUMMYFUNCTION("""COMPUTED_VALUE"""),6081081.0) -> 6081081 | J23: =IFERROR(__xludf.DUMMYFUNCTION("""COMPUTED_VALUE"""),668919.0) -> 668919 | L23: =IFERROR(__xludf.DUMMYFUNCTION("""COMPUTED_VALUE"""),6750000.0) -> 6750000 | M23: 45903 | N23: BCA MPG | O23: 6750000 | P23: 45903 | R23: =L23-O23 -> 0 | S23: =IF(R23>0,"ost","-") -> - | T23: - | U23: WhatsApp Image 2025-09-03 at 17.04.35.jpeg
B24: =IFERROR(__xludf.DUMMYFUNCTION("""COMPUTED_VALUE"""),"Top Point") -> Top Point | C24: =IFERROR(__xludf.DUMMYFUNCTION("""COMPUTED_VALUE"""),"Pembelian Kekurangan Stock Suntikan RSUD") -> Pembelian Kekurangan Stock Suntikan RSUD | E24: =IFERROR(__xludf.DUMMYFUNCTION("""COMPUTED_VALUE"""),"Surat Pesanan Suntikan RSUD Cibinong") -> Surat Pesanan Suntikan RSUD Cibinong | F24: =IFERROR(__xludf.DUMMYFUNCTION("""COMPUTED_VALUE"""),"PO ke TOP POINT (stok suntikan rsud)") -> PO ke TOP POINT (stok suntikan rsud) | G24: =IFERROR(__xludf.DUMMYFUNCTION("""COMPUTED_VALUE"""),45897.0) -> 45897 | I24: =IFERROR(__xludf.DUMMYFUNCTION("""COMPUTED_VALUE"""),3386086.0) -> 3386086 | J24: =IFERROR(__xludf.DUMMYFUNCTION("""COMPUTED_VALUE"""),372469.0) -> 372469 | L24: =IFERROR(__xludf.DUMMYFUNCTION("""COMPUTED_VALUE"""),3758555.0) -> 3758555 | M24: 45903 | N24: BCA MPG | O24: 3758555 | P24: 45903 | R24: =L24-O24 -> 0 | S24: =IF(R24>0,"ost","-") -> - | T24: - | U24: WhatsApp Image 2025-09-03 at 17.04.23.jpeg
B25: =IFERROR(__xludf.DUMMYFUNCTION("""COMPUTED_VALUE"""),"Sarana Megamedilab Sejahtera (SMS)") -> Sarana Megamedilab Sejahtera (SMS) | C25: =IFERROR(__xludf.DUMMYFUNCTION("""COMPUTED_VALUE"""),"Pembelian Reagen RSUD Cibinong (Nodin 15)") -> Pembelian Reagen RSUD Cibinong (Nodin 15) | D25: =IFERROR(__xludf.DUMMYFUNCTION("""COMPUTED_VALUE"""),"SPH RSUD CIBINONG NODIN 15 (1).pdf") -> SPH RSUD CIBINONG NODIN 15 (1).pdf | E25: =IFERROR(__xludf.DUMMYFUNCTION("""COMPUTED_VALUE"""),"nodin 15 rsud cibinong") -> nodin 15 rsud cibinong | F25: =IFERROR(__xludf.DUMMYFUNCTION("""COMPUTED_VALUE"""),"PO ke SMS (nodin 15 RSUD Cibinong)") -> PO ke SMS (nodin 15 RSUD Cibinong) | G25: =IFERROR(__xludf.DUMMYFUNCTION("""COMPUTED_VALUE"""),45876.0) -> 45876 | I25: =IFERROR(__xludf.DUMMYFUNCTION("""COMPUTED_VALUE"""),1.228401E7) -> 12284010 | J25: =IFERROR(__xludf.DUMMYFUNCTION("""COMPUTED_VALUE"""),1351241.0) -> 1351241 | L25: =IFERROR(__xludf.DUMMYFUNCTION("""COMPUTED_VALUE"""),1.3635251E7) -> 13635251 | M25: 45904 | N25: BCA MPG | O25: 13635251 | P25: 45904 | R25: =L25-O25 -> 0 | S25: =IF(R25>0,"ost","-") -> - | T25: -
B26: =IFERROR(__xludf.DUMMYFUNCTION("""COMPUTED_VALUE"""),"PT. Burhan Sejahtera Mulia") -> PT. Burhan Sejahtera Mulia | C26: =IFERROR(__xludf.DUMMYFUNCTION("""COMPUTED_VALUE"""),"Pembelian Pesanan (PKM Bojong) Reagen Asam Urat") -> Pembelian Pesanan (PKM Bojong) Reagen Asam Urat | E26: =IFERROR(__xludf.DUMMYFUNCTION("""COMPUTED_VALUE"""),"part of SO no.20") -> part of SO no.20 | F26: =IFERROR(__xludf.DUMMYFUNCTION("""COMPUTED_VALUE"""),"PO MPG-080925003 BSM.pdf") -> PO MPG-080925003 BSM.pdf | G26: =IFERROR(__xludf.DUMMYFUNCTION("""COMPUTED_VALUE"""),45908.0) -> 45908 | I26: =IFERROR(__xludf.DUMMYFUNCTION("""COMPUTED_VALUE"""),720440.0) -> 720440 | J26: =IFERROR(__xludf.DUMMYFUNCTION("""COMPUTED_VALUE"""),79248.0) -> 79248 | L26: =IFERROR(__xludf.DUMMYFUNCTION("""COMPUTED_VALUE"""),799688.0) -> 799688 | M26: 45908 | N26: BCA MPG | O26: 799688 | P26: 45908 | R26: =L26-O26 -> 0 | S26: =IF(R26>0,"ost","-") -> - | T26: -
B27: =IFERROR(__xludf.DUMMYFUNCTION("""COMPUTED_VALUE"""),"Shopee") -> Shopee | C27: =IFERROR(__xludf.DUMMYFUNCTION("""COMPUTED_VALUE"""),"Pembelanjaan Pesanan Tambahan (PKM Bojong) Carpule dan Plastik Sampah Medis") -> Pembelanjaan Pesanan Tambahan (PKM Bojong) Carpule dan Plastik Sampah Medis | E27: =IFERROR(__xludf.DUMMYFUNCTION("""COMPUTED_VALUE"""),"-Menyusul-") -> -Menyusul- | G27: =IFERROR(__xludf.DUMMYFUNCTION("""COMPUTED_VALUE"""),45908.0) -> 45908 | I27: =IFERROR(__xludf.DUMMYFUNCTION("""COMPUTED_VALUE"""),543000.0) -> 543000 | L27: =IFERROR(__xludf.DUMMYFUNCTION("""COMPUTED_VALUE"""),543000.0) -> 543000 | M27: 45908 | N27: BCA MPG | O27: 543000 | P27: 45908 | R27: =L27-O27 -> 0 | S27: =IF(R27>0,"ost","-") -> - | T27: -
B28: =IFERROR(__xludf.DUMMYFUNCTION("""COMPUTED_VALUE"""),"PT. Tirta Investama") -> PT. Tirta Investama | C28: =IFERROR(__xludf.DUMMYFUNCTION("""COMPUTED_VALUE"""),"Pembaayaran Aqua Galon Gedung") -> Pembaayaran Aqua Galon Gedung | G28: =IFERROR(__xludf.DUMMYFUNCTION("""COMPUTED_VALUE"""),45900.0) -> 45900 | I28: =IFERROR(__xludf.DUMMYFUNCTION("""COMPUTED_VALUE"""),400000.0) -> 400000 | L28: =IFERROR(__xludf.DUMMYFUNCTION("""COMPUTED_VALUE"""),400000.0) -> 400000 | M28: 45908 | N28: BCA MPG | O28: 400000 | P28: 45908 | R28: =L28-O28 -> 0 | S28: =IF(R28>0,"ost","-") -> - | T28: -
B29: =IFERROR(__xludf.DUMMYFUNCTION("""COMPUTED_VALUE"""),"PT. Top Point Medical") -> PT. Top Point Medical | C29: =IFERROR(__xludf.DUMMYFUNCTION("""COMPUTED_VALUE"""),"Pembellian Pesanan (RSPP) PO ke 4") -> Pembellian Pesanan (RSPP) PO ke 4 | E29: =IFERROR(__xludf.DUMMYFUNCTION("""COMPUTED_VALUE"""),"PO KE 4 RSPP") -> PO KE 4 RSPP | F29: =IFERROR(__xludf.DUMMYFUNCTION("""COMPUTED_VALUE"""),"po ke tp (rspp ke 4)") -> po ke tp (rspp ke 4) | G29: =IFERROR(__xludf.DUMMYFUNCTION("""COMPUTED_VALUE"""),45909.0) -> 45909 | I29: =IFERROR(__xludf.DUMMYFUNCTION("""COMPUTED_VALUE"""),4560811.0) -> 4560811 | J29: =IFERROR(__xludf.DUMMYFUNCTION("""COMPUTED_VALUE"""),501689.0) -> 501689 | L29: =IFERROR(__xludf.DUMMYFUNCTION("""COMPUTED_VALUE"""),5062500.0) -> 5062500 | M29: 45915 | N29: BCA MPG | O29: 5062500 | P29: 45915 | R29: =L29-O29 -> 0 | S29: =IF(R29>0,"ost","-") -> - | T29: -
B30: =IFERROR(__xludf.DUMMYFUNCTION("""COMPUTED_VALUE"""),"Gedung") -> Gedung | C30: =IFERROR(__xludf.DUMMYFUNCTION("""COMPUTED_VALUE"""),"Pembayaran Listrik dan Parkir Gedung (pemakaian agustus)") -> Pembayaran Listrik dan Parkir Gedung (pemakaian agustus) | G30: =IFERROR(__xludf.DUMMYFUNCTION("""COMPUTED_VALUE"""),45915.0) -> 45915 | I30: =IFERROR(__xludf.DUMMYFUNCTION("""COMPUTED_VALUE"""),4684781.0) -> 4684781 | L30: =IFERROR(__xludf.DUMMYFUNCTION("""COMPUTED_VALUE"""),4684781.0) -> 4684781 | M30: 45915 | N30: BCA MPG | O30: 4684781 | P30: 45915 | R30: =L30-O30 -> 0 | S30: =IF(R30>0,"ost","-") -> - | T30: -
B31: =IFERROR(__xludf.DUMMYFUNCTION("""COMPUTED_VALUE"""),"Shopee") -> Shopee | C31: =IFERROR(__xludf.DUMMYFUNCTION("""COMPUTED_VALUE"""),"Pembelian Kekurangan Plastik Sampah Medis (PKM Bojong)") -> Pembelian Kekurangan Plastik Sampah Medis (PKM Bojong) | E31: =IFERROR(__xludf.DUMMYFUNCTION("""COMPUTED_VALUE"""),"NOTA PERABOT KANTOR MATA PENSIL 09 25.pdf") -> NOTA PERABOT KANTOR MATA PENSIL 09 25.pdf | G31: =IFERROR(__xludf.DUMMYFUNCTION("""COMPUTED_VALUE"""),45915.0) -> 45915 | I31: =IFERROR(__xludf.DUMMYFUNCTION("""COMPUTED_VALUE"""),53380.0) -> 53380 | L31: =IFERROR(__xludf.DUMMYFUNCTION("""COMPUTED_VALUE"""),53380.0) -> 53380 | M31: 45915 | N31: BCA MPG | O31: 53380 | P31: 45915 | R31: =L31-O31 -> 0 | S31: =IF(R31>0,"ost","-") -> - | T31: -
B32: =IFERROR(__xludf.DUMMYFUNCTION("""COMPUTED_VALUE"""),"Shopee") -> Shopee | C32: =IFERROR(__xludf.DUMMYFUNCTION("""COMPUTED_VALUE"""),"Pembelian Kontrol Kimia (PKM Balekambang)") -> Pembelian Kontrol Kimia (PKM Balekambang) | E32: =IFERROR(__xludf.DUMMYFUNCTION("""COMPUTED_VALUE"""),"Pesanan Balekambang ") -> Pesanan Balekambang | G32: =IFERROR(__xludf.DUMMYFUNCTION("""COMPUTED_VALUE"""),45916.0) -> 45916 | I32: =IFERROR(__xludf.DUMMYFUNCTION("""COMPUTED_VALUE"""),1277500.0) -> 1277500 | L32: =IFERROR(__xludf.DUMMYFUNCTION("""COMPUTED_VALUE"""),1277500.0) -> 1277500 | M32: 45916 | N32: BCA MPG | O32: 1277500 | P32: 45916 | R32: =L32-O32 -> 0 | S32: =IF(R32>0,"ost","-") -> - | T32: -
B33: =IFERROR(__xludf.DUMMYFUNCTION("""COMPUTED_VALUE"""),"Shopee") -> Shopee | C33: =IFERROR(__xludf.DUMMYFUNCTION("""COMPUTED_VALUE"""),"Pembelian Pesanan (PKM Cipeucang)") -> Pembelian Pesanan (PKM Cipeucang) | E33: =IFERROR(__xludf.DUMMYFUNCTION("""COMPUTED_VALUE"""),"Surat Pesanan BMHP PKM Cipeucang.pdf") -> Surat Pesanan BMHP PKM Cipeucang.pdf | G33: =IFERROR(__xludf.DUMMYFUNCTION("""COMPUTED_VALUE"""),45917.0) -> 45917 | I33: =IFERROR(__xludf.DUMMYFUNCTION("""COMPUTED_VALUE"""),2676315.0) -> 2676315 | L33: =IFERROR(__xludf.DUMMYFUNCTION("""COMPUTED_VALUE"""),2676315.0) -> 2676315 | M33: 45917 | N33: BCA MPG | O33: 2676315 | P33: 45917 | R33: =L33-O33 -> 0 | S33: =IF(R33>0,"ost","-") -> - | T33: -
B34: =IFERROR(__xludf.DUMMYFUNCTION("""COMPUTED_VALUE"""),"Shopee") -> Shopee | C34: =IFERROR(__xludf.DUMMYFUNCTION("""COMPUTED_VALUE"""),"Pembelian Pesanan (PKM Kelapa Dua) Plastik Sampah") -> Pembelian Pesanan (PKM Kelapa Dua) Plastik Sampah | E34: =IFERROR(__xludf.DUMMYFUNCTION("""COMPUTED_VALUE"""),"SP Belanja Kebersihan Puskesmas Kelapa Dua September 2025.pdf") -> SP Belanja Kebersihan Puskesmas Kelapa Dua September 2025.pdf | G34: =IFERROR(__xludf.DUMMYFUNCTION("""COMPUTED_VALUE"""),45925.0) -> 45925 | I34: =IFERROR(__xludf.DUMMYFUNCTION("""COMPUTED_VALUE"""),1827490.0) -> 1827490 | L34: =IFERROR(__xludf.DUMMYFUNCTION("""COMPUTED_VALUE"""),1827490.0) -> 1827490 | M34: 45925 | N34: BCA MPG | O34: 1827490 | P34: 45925 | R34: =L34-O34 -> 0 | S34: =IF(R34>0,"ost","-") -> - | T34: -
B35: =IFERROR(__xludf.DUMMYFUNCTION("""COMPUTED_VALUE"""),"Shopee") -> Shopee | C35: =IFERROR(__xludf.DUMMYFUNCTION("""COMPUTED_VALUE"""),"Pembelian Pesanan (PKM Kelapa Dua) Pengharum Ruangan spray dan gantung dahlia") -> Pembelian Pesanan (PKM Kelapa Dua) Pengharum Ruangan spray dan gantung dahlia | E35: =IFERROR(__xludf.DUMMYFUNCTION("""COMPUTED_VALUE"""),"SP Belanja Kebersihan Puskesmas Kelapa Dua September 2025.pdf") -> SP Belanja Kebersihan Puskesmas Kelapa Dua September 2025.pdf | G35: =IFERROR(__xludf.DUMMYFUNCTION("""COMPUTED_VALUE"""),45925.0) -> 45925 | I35: =IFERROR(__xludf.DUMMYFUNCTION("""COMPUTED_VALUE"""),937200.0) -> 937200 | L35: =IFERROR(__xludf.DUMMYFUNCTION("""COMPUTED_VALUE"""),937200.0) -> 937200 | M35: 45925 | N35: BCA MPG | O35: 937200 | P35: 45925 | R35: =L35-O35 -> 0 | S35: =IF(R35>0,"ost","-") -> - | T35: -
B36: =IFERROR(__xludf.DUMMYFUNCTION("""COMPUTED_VALUE"""),"Shopee") -> Shopee | C36: =IFERROR(__xludf.DUMMYFUNCTION("""COMPUTED_VALUE"""),"Pembelian Pesanan (PKM Kelapa Dua) tissue livi dan paseo") -> Pembelian Pesanan (PKM Kelapa Dua) tissue livi dan paseo | E36: =IFERROR(__xludf.DUMMYFUNCTION("""COMPUTED_VALUE"""),"SP Belanja Kebersihan Puskesmas Kelapa Dua September 2025.pdf") -> SP Belanja Kebersihan Puskesmas Kelapa Dua September 2025.pdf | G36: =IFERROR(__xludf.DUMMYFUNCTION("""COMPUTED_VALUE"""),45925.0) -> 45925 | I36: =IFERROR(__xludf.DUMMYFUNCTION("""COMPUTED_VALUE"""),480255.0) -> 480255 | L36: =IFERROR(__xludf.DUMMYFUNCTION("""COMPUTED_VALUE"""),480255.0) -> 480255 | M36: 45925 | N36: BCA MPG | O36: 480255 | P36: 45925 | R36: =L36-O36 -> 0 | S36: =IF(R36>0,"ost","-") -> - | T36: -
B37: =IFERROR(__xludf.DUMMYFUNCTION("""COMPUTED_VALUE"""),"Shopee") -> Shopee | C37: =IFERROR(__xludf.DUMMYFUNCTION("""COMPUTED_VALUE"""),"Pembelian Pesanan (PKM Kelapa Dua) Baygon") -> Pembelian Pesanan (PKM Kelapa Dua) Baygon | E37: =IFERROR(__xludf.DUMMYFUNCTION("""COMPUTED_VALUE"""),"SP Belanja Kebersihan Puskesmas Kelapa Dua September 2025.pdf") -> SP Belanja Kebersihan Puskesmas Kelapa Dua September 2025.pdf | G37: =IFERROR(__xludf.DUMMYFUNCTION("""COMPUTED_VALUE"""),45925.0) -> 45925 | I37: =IFERROR(__xludf.DUMMYFUNCTION("""COMPUTED_VALUE"""),798000.0) -> 798000 | L37: =IFERROR(__xludf.DUMMYFUNCTION("""COMPUTED_VALUE"""),798000.0) -> 798000 | M37: 45925 | N37: BCA MPG | O37: 798000 | P37: 45925 | R37: =L37-O37 -> 0 | S37: =IF(R37>0,"ost","-") -> - | T37: -
B38: =IFERROR(__xludf.DUMMYFUNCTION("""COMPUTED_VALUE"""),"Shopee") -> Shopee | C38: =IFERROR(__xludf.DUMMYFUNCTION("""COMPUTED_VALUE"""),"Pembelian Pesanan (PKM Kelapa Dua) switzal dan minyak telon") -> Pembelian Pesanan (PKM Kelapa Dua) switzal dan minyak telon | E38: =IFERROR(__xludf.DUMMYFUNCTION("""COMPUTED_VALUE"""),"SP Belanja Kebersihan Puskesmas Kelapa Dua September 2025.pdf") -> SP Belanja Kebersihan Puskesmas Kelapa Dua September 2025.pdf | G38: =IFERROR(__xludf.DUMMYFUNCTION("""COMPUTED_VALUE"""),45925.0) -> 45925 | I38: =IFERROR(__xludf.DUMMYFUNCTION("""COMPUTED_VALUE"""),493200.0) -> 493200 | L38: =IFERROR(__xludf.DUMMYFUNCTION("""COMPUTED_VALUE"""),493200.0) -> 493200 | M38: 45925 | N38: BCA MPG | O38: 493200 | P38: 45925 | R38: =L38-O38 -> 0 | S38: =IF(R38>0,"ost","-") -> - | T38: -
B39: =IFERROR(__xludf.DUMMYFUNCTION("""COMPUTED_VALUE"""),"Shopee") -> Shopee | C39: =IFERROR(__xludf.DUMMYFUNCTION("""COMPUTED_VALUE"""),"Pembelian Pesanan (PKM Kelapa Dua) kamper") -> Pembelian Pesanan (PKM Kelapa Dua) kamper | E39: =IFERROR(__xludf.DUMMYFUNCTION("""COMPUTED_VALUE"""),"SP Belanja Kebersihan Puskesmas Kelapa Dua September 2025.pdf") -> SP Belanja Kebersihan Puskesmas Kelapa Dua September 2025.pdf | G39: =IFERROR(__xludf.DUMMYFUNCTION("""COMPUTED_VALUE"""),45925.0) -> 45925 | I39: =IFERROR(__xludf.DUMMYFUNCTION("""COMPUTED_VALUE"""),622900.0) -> 622900 | L39: =IFERROR(__xludf.DUMMYFUNCTION("""COMPUTED_VALUE"""),622900.0) -> 622900 | M39: 45925 | N39: BCA MPG | O39: 622900 | P39: 45925 | R39: =L39-O39 -> 0 | S39: =IF(R39>0,"ost","-") -> - | T39: -
B40: =IFERROR(__xludf.DUMMYFUNCTION("""COMPUTED_VALUE"""),"Shopee") -> Shopee | C40: =IFERROR(__xludf.DUMMYFUNCTION("""COMPUTED_VALUE"""),"Pembelian Pesanan (PKM Kelapa Dua) tempat sampah") -> Pembelian Pesanan (PKM Kelapa Dua) tempat sampah | E40: =IFERROR(__xludf.DUMMYFUNCTION("""COMPUTED_VALUE"""),"SP Belanja Kebersihan Puskesmas Kelapa Dua September 2025.pdf") -> SP Belanja Kebersihan Puskesmas Kelapa Dua September 2025.pdf | G40: =IFERROR(__xludf.DUMMYFUNCTION("""COMPUTED_VALUE"""),45925.0) -> 45925 | I40: =IFERROR(__xludf.DUMMYFUNCTION("""COMPUTED_VALUE"""),432000.0) -> 432000 | L40: =IFERROR(__xludf.DUMMYFUNCTION("""COMPUTED_VALUE"""),432000.0) -> 432000 | M40: 45925 | N40: BCA MPG | O40: 432000 | P40: 45925 | R40: =L40-O40 -> 0 | S40: =IF(R40>0,"ost","-") -> - | T40: -
B41: =IFERROR(__xludf.DUMMYFUNCTION("""COMPUTED_VALUE"""),"Shopee") -> Shopee | C41: =IFERROR(__xludf.DUMMYFUNCTION("""COMPUTED_VALUE"""),"Pembelian Pesanan (PKM Kelapa Dua) sapu,ember,sikat,keset,sapu plafon,air spray") -> Pembelian Pesanan (PKM Kelapa Dua) sapu,ember,sikat,keset,sapu plafon,air spray | E41: =IFERROR(__xludf.DUMMYFUNCTION("""COMPUTED_VALUE"""),"SP Belanja Kebersihan Puskesmas Kelapa Dua September 2025.pdf") -> SP Belanja Kebersihan Puskesmas Kelapa Dua September 2025.pdf | G41: =IFERROR(__xludf.DUMMYFUNCTION("""COMPUTED_VALUE"""),45925.0) -> 45925 | I41: =IFERROR(__xludf.DUMMYFUNCTION("""COMPUTED_VALUE"""),601325.0) -> 601325 | L41: =IFERROR(__xludf.DUMMYFUNCTION("""COMPUTED_VALUE"""),601325.0) -> 601325 | M41: 45925 | N41: BCA MPG | O41: 601325 | P41: 45925 | R41: =L41-O41 -> 0 | S41: =IF(R41>0,"ost","-") -> - | T41: -
B42: =IFERROR(__xludf.DUMMYFUNCTION("""COMPUTED_VALUE"""),"PT. Top Point") -> PT. Top Point | C42: =IFERROR(__xludf.DUMMYFUNCTION("""COMPUTED_VALUE"""),"Pembelian Pesanan RSPP PO ke 5") -> Pembelian Pesanan RSPP PO ke 5 | E42: =IFERROR(__xludf.DUMMYFUNCTION("""COMPUTED_VALUE"""),"Surat Pesanan RSPP Po 5") -> Surat Pesanan RSPP Po 5 | F42: =IFERROR(__xludf.DUMMYFUNCTION("""COMPUTED_VALUE"""),"PO ke TP RSPP PO 5") -> PO ke TP RSPP PO 5 | G42: =IFERROR(__xludf.DUMMYFUNCTION("""COMPUTED_VALUE"""),45918.0) -> 45918 | I42: =IFERROR(__xludf.DUMMYFUNCTION("""COMPUTED_VALUE"""),4560811.0) -> 4560811 | J42: =IFERROR(__xludf.DUMMYFUNCTION("""COMPUTED_VALUE"""),501689.0) -> 501689 | L42: =IFERROR(__xludf.DUMMYFUNCTION("""COMPUTED_VALUE"""),5062500.0) -> 5062500 | M42: 45925 | N42: BCA MPG | O42: 5062500 | P42: 45925 | R42: =L42-O42 -> 0 | S42: =IF(R42>0,"ost","-") -> - | T42: -
B43: =IFERROR(__xludf.DUMMYFUNCTION("""COMPUTED_VALUE"""),"PT. Sangiang Karya Mandiri") -> PT. Sangiang Karya Mandiri | C43: =IFERROR(__xludf.DUMMYFUNCTION("""COMPUTED_VALUE"""),"Pembelian Pesanan Dinkes Tasikmalaya") -> Pembelian Pesanan Dinkes Tasikmalaya | E43: =IFERROR(__xludf.DUMMYFUNCTION("""COMPUTED_VALUE"""),"SP 46 Genta (1).pdf") -> SP 46 Genta (1).pdf | F43: =IFERROR(__xludf.DUMMYFUNCTION("""COMPUTED_VALUE"""),"po ke pt.sangiang") -> po ke pt.sangiang | G43: =IFERROR(__xludf.DUMMYFUNCTION("""COMPUTED_VALUE"""),45925.0) -> 45925 | I43: =IFERROR(__xludf.DUMMYFUNCTION("""COMPUTED_VALUE"""),4375000.0) -> 4375000 | J43: =IFERROR(__xludf.DUMMYFUNCTION("""COMPUTED_VALUE"""),481250.0) -> 481250 | L43: =IFERROR(__xludf.DUMMYFUNCTION("""COMPUTED_VALUE"""),4856250.0) -> 4856250 | M43: 45925 | N43: BCA MPG | O43: 4856250 | P43: 45925 | R43: =L43-O43 -> 0 | S43: =IF(R43>0,"ost","-") -> - | T43: -
B44: =IFERROR(__xludf.DUMMYFUNCTION("""COMPUTED_VALUE"""),"Shopee") -> Shopee | C44: =IFERROR(__xludf.DUMMYFUNCTION("""COMPUTED_VALUE"""),"Pembelian Pesanan (PKM Kelapa Dua) mop pel, kain lap, sikat gagang") -> Pembelian Pesanan (PKM Kelapa Dua) mop pel, kain lap, sikat gagang | E44: =IFERROR(__xludf.DUMMYFUNCTION("""COMPUTED_VALUE"""),"SP Belanja Kebersihan Puskesmas Kelapa Dua September 2025.pdf") -> SP Belanja Kebersihan Puskesmas Kelapa Dua September 2025.pdf | G44: =IFERROR(__xludf.DUMMYFUNCTION("""COMPUTED_VALUE"""),45925.0) -> 45925 | I44: =IFERROR(__xludf.DUMMYFUNCTION("""COMPUTED_VALUE"""),413664.0) -> 413664 | L44: =IFERROR(__xludf.DUMMYFUNCTION("""COMPUTED_VALUE"""),413664.0) -> 413664 | M44: 45925 | N44: BCA MPG | O44: 413664 | P44: 45925 | R44: =L44-O44 -> 0 | S44: =IF(R44>0,"ost","-") -> - | T44: -
B45: =IFERROR(__xludf.DUMMYFUNCTION("""COMPUTED_VALUE"""),"Shopee") -> Shopee | C45: =IFERROR(__xludf.DUMMYFUNCTION("""COMPUTED_VALUE"""),"Pembelian Pesanan (PKM Kelapa Dua) pembersih kaca") -> Pembelian Pesanan (PKM Kelapa Dua) pembersih kaca | E45: =IFERROR(__xludf.DUMMYFUNCTION("""COMPUTED_VALUE"""),"SP Belanja Kebersihan Puskesmas Kelapa Dua September 2025.pdf") -> SP Belanja Kebersihan Puskesmas Kelapa Dua September 2025.pdf | G45: =IFERROR(__xludf.DUMMYFUNCTION("""COMPUTED_VALUE"""),45925.0) -> 45925 | I45: =IFERROR(__xludf.DUMMYFUNCTION("""COMPUTED_VALUE"""),378500.0) -> 378500 | L45: =IFERROR(__xludf.DUMMYFUNCTION("""COMPUTED_VALUE"""),378500.0) -> 378500 | M45: 45925 | N45: BCA MPG | O45: 378500 | P45: 45925 | R45: =L45-O45 -> 0 | S45: =IF(R45>0,"ost","-") -> - | T45: -
B46: =IFERROR(__xludf.DUMMYFUNCTION("""COMPUTED_VALUE"""),"Shopee") -> Shopee | C46: =IFERROR(__xludf.DUMMYFUNCTION("""COMPUTED_VALUE"""),"Pembelian Pesanan (PKM Kelapa Dua) hand sanitizer") -> Pembelian Pesanan (PKM Kelapa Dua) hand sanitizer | E46: =IFERROR(__xludf.DUMMYFUNCTION("""COMPUTED_VALUE"""),"SP Belanja Kebersihan Puskesmas Kelapa Dua September 2025.pdf") -> SP Belanja Kebersihan Puskesmas Kelapa Dua September 2025.pdf | G46: =IFERROR(__xludf.DUMMYFUNCTION("""COMPUTED_VALUE"""),45925.0) -> 45925 | I46: =IFERROR(__xludf.DUMMYFUNCTION("""COMPUTED_VALUE"""),436963.0) -> 436963 | L46: =IFERROR(__xludf.DUMMYFUNCTION("""COMPUTED_VALUE"""),436963.0) -> 436963 | M46: 45925 | N46: BCA MPG | O46: 436963 | P46: 45925 | R46: =L46-O46 -> 0
B47: =IFERROR(__xludf.DUMMYFUNCTION("""COMPUTED_VALUE"""),"Shopee") -> Shopee | C47: =IFERROR(__xludf.DUMMYFUNCTION("""COMPUTED_VALUE"""),"Pembelian Pesanan (PKM Kelapa Dua) karbol, cuci tangan, cuci piring") -> Pembelian Pesanan (PKM Kelapa Dua) karbol, cuci tangan, cuci piring | E47: =IFERROR(__xludf.DUMMYFUNCTION("""COMPUTED_VALUE"""),"SP Belanja Kebersihan Puskesmas Kelapa Dua September 2025.pdf") -> SP Belanja Kebersihan Puskesmas Kelapa Dua September 2025.pdf | G47: =IFERROR(__xludf.DUMMYFUNCTION("""COMPUTED_VALUE"""),45925.0) -> 45925 | I47: =IFERROR(__xludf.DUMMYFUNCTION("""COMPUTED_VALUE"""),565800.0) -> 565800 | L47: =IFERROR(__xludf.DUMMYFUNCTION("""COMPUTED_VALUE"""),565800.0) -> 565800 | M47: 45925 | N47: BCA MPG | O47: 565800 | P47: 45925 | R47: =L47-O47 -> 0
B48: =IFERROR(__xludf.DUMMYFUNCTION("""COMPUTED_VALUE"""),"Shopee") -> Shopee | C48: =IFERROR(__xludf.DUMMYFUNCTION("""COMPUTED_VALUE"""),"Pembelian Pesanan (PKM Kelapa Dua) byclin") -> Pembelian Pesanan (PKM Kelapa Dua) byclin | E48: =IFERROR(__xludf.DUMMYFUNCTION("""COMPUTED_VALUE"""),"SP Belanja Kebersihan Puskesmas Kelapa Dua September 2025.pdf") -> SP Belanja Kebersihan Puskesmas Kelapa Dua September 2025.pdf | G48: =IFERROR(__xludf.DUMMYFUNCTION("""COMPUTED_VALUE"""),45925.0) -> 45925 | I48: =IFERROR(__xludf.DUMMYFUNCTION("""COMPUTED_VALUE"""),509557.0) -> 509557 | L48: =IFERROR(__xludf.DUMMYFUNCTION("""COMPUTED_VALUE"""),509557.0) -> 509557 | M48: 45925 | N48: BCA MPG | O48: 509557 | P48: 45925 | R48: =L48-O48 -> 0
B49: =IFERROR(__xludf.DUMMYFUNCTION("""COMPUTED_VALUE"""),"Shopee") -> Shopee | C49: =IFERROR(__xludf.DUMMYFUNCTION("""COMPUTED_VALUE"""),"Pembelian Pesanan (PKM Kelapa Dua) porstex") -> Pembelian Pesanan (PKM Kelapa Dua) porstex | E49: =IFERROR(__xludf.DUMMYFUNCTION("""COMPUTED_VALUE"""),"SP Belanja Kebersihan Puskesmas Kelapa Dua September 2025.pdf") -> SP Belanja Kebersihan Puskesmas Kelapa Dua September 2025.pdf | G49: =IFERROR(__xludf.DUMMYFUNCTION("""COMPUTED_VALUE"""),45925.0) -> 45925 | I49: =IFERROR(__xludf.DUMMYFUNCTION("""COMPUTED_VALUE"""),710160.0) -> 710160 | L49: =IFERROR(__xludf.DUMMYFUNCTION("""COMPUTED_VALUE"""),710160.0) -> 710160 | M49: 45925 | N49: BCA MPG | O49: 710160 | P49: 45925 | R49: =L49-O49 -> 0
B50: =IFERROR(__xludf.DUMMYFUNCTION("""COMPUTED_VALUE"""),"Shopee") -> Shopee | C50: =IFERROR(__xludf.DUMMYFUNCTION("""COMPUTED_VALUE"""),"Pembelian Pesanan (PKM Bojong Gede) Spons Sapu Lidi Sapu lantai kain pel") -> Pembelian Pesanan (PKM Bojong Gede) Spons Sapu Lidi Sapu lantai kain pel | E50: =IFERROR(__xludf.DUMMYFUNCTION("""COMPUTED_VALUE"""),"surat-pesanan-EP-01K64RKYR001N8JKV3440C0J3N Pkm Bojong Gede (1).pdf") -> surat-pesanan-EP-01K64RKYR001N8JKV3440C0J3N Pkm Bojong Gede (1).pdf | G50: =IFERROR(__xludf.DUMMYFUNCTION("""COMPUTED_VALUE"""),45930.0) -> 45930 | I50: =IFERROR(__xludf.DUMMYFUNCTION("""COMPUTED_VALUE"""),356981.0) -> 356981 | L50: =IFERROR(__xludf.DUMMYFUNCTION("""COMPUTED_VALUE"""),356981.0) -> 356981 | M50: 45930 | N50: BCA MPG | O50: 356981 | P50: 45930 | R50: =L50-O50 -> 0
B51: =IFERROR(__xludf.DUMMYFUNCTION("""COMPUTED_VALUE"""),"Shopee") -> Shopee | C51: =IFERROR(__xludf.DUMMYFUNCTION("""COMPUTED_VALUE"""),"Pembelian Pesanan (PKM Bojong Gede) Karbol dan Sabun cuci tangan") -> Pembelian Pesanan (PKM Bojong Gede) Karbol dan Sabun cuci tangan | E51: =IFERROR(__xludf.DUMMYFUNCTION("""COMPUTED_VALUE"""),"surat-pesanan-EP-01K64RKYR001N8JKV3440C0J3N Pkm Bojong Gede (1).pdf") -> surat-pesanan-EP-01K64RKYR001N8JKV3440C0J3N Pkm Bojong Gede (1).pdf | G51: =IFERROR(__xludf.DUMMYFUNCTION("""COMPUTED_VALUE"""),45930.0) -> 45930 | I51: =IFERROR(__xludf.DUMMYFUNCTION("""COMPUTED_VALUE"""),1255860.0) -> 1255860 | L51: =IFERROR(__xludf.DUMMYFUNCTION("""COMPUTED_VALUE"""),1255860.0) -> 1255860 | M51: 45930 | N51: BCA MPG | O51: 1255860 | P51: 45930 | R51: =L51-O51 -> 0
B52: =IFERROR(__xludf.DUMMYFUNCTION("""COMPUTED_VALUE"""),"Shopee") -> Shopee | C52: =IFERROR(__xludf.DUMMYFUNCTION("""COMPUTED_VALUE"""),"Pembelian Pesanan (PKM Bojong Gede) Tissue") -> Pembelian Pesanan (PKM Bojong Gede) Tissue | E52: =IFERROR(__xludf.DUMMYFUNCTION("""COMPUTED_VALUE"""),"surat-pesanan-EP-01K64RKYR001N8JKV3440C0J3N Pkm Bojong Gede (1).pdf") -> surat-pesanan-EP-01K64RKYR001N8JKV3440C0J3N Pkm Bojong Gede (1).pdf | G52: =IFERROR(__xludf.DUMMYFUNCTION("""COMPUTED_VALUE"""),45930.0) -> 45930 | I52: =IFERROR(__xludf.DUMMYFUNCTION("""COMPUTED_VALUE"""),912900.0) -> 912900 | L52: =IFERROR(__xludf.DUMMYFUNCTION("""COMPUTED_VALUE"""),912900.0) -> 912900 | M52: 45930 | N52: BCA MPG | O52: 912900 | P52: 45930 | R52: =L52-O52 -> 0
B53: =IFERROR(__xludf.DUMMYFUNCTION("""COMPUTED_VALUE"""),"PT. Bintang Setya Media") -> PT. Bintang Setya Media | C53: =IFERROR(__xludf.DUMMYFUNCTION("""COMPUTED_VALUE"""),"Pembayaran Service Printer") -> Pembayaran Service Printer | G53: =IFERROR(__xludf.DUMMYFUNCTION("""COMPUTED_VALUE"""),45919.0) -> 45919 | I53: =IFERROR(__xludf.DUMMYFUNCTION("""COMPUTED_VALUE"""),780000.0) -> 780000 | L53: =IFERROR(__xludf.DUMMYFUNCTION("""COMPUTED_VALUE"""),780000.0) -> 780000 | M53: 45930 | N53: BCA MPG | O53: 780000 | P53: 45930 | R53: =L53-O53 -> 0
B54: =IFERROR(__xludf.DUMMYFUNCTION("""COMPUTED_VALUE"""),"PT. Bintang Setya Media") -> PT. Bintang Setya Media | C54: =IFERROR(__xludf.DUMMYFUNCTION("""COMPUTED_VALUE"""),"Pembelian Tinta Printer") -> Pembelian Tinta Printer | G54: =IFERROR(__xludf.DUMMYFUNCTION("""COMPUTED_VALUE"""),45919.0) -> 45919 | I54: =IFERROR(__xludf.DUMMYFUNCTION("""COMPUTED_VALUE"""),500000.0) -> 500000 | L54: =IFERROR(__xludf.DUMMYFUNCTION("""COMPUTED_VALUE"""),500000.0) -> 500000 | M54: 45930 | N54: BCA MPG | O54: 500000 | P54: 45930 | R54: =L54-O54 -> 0
B55: =IFERROR(__xludf.DUMMYFUNCTION("""COMPUTED_VALUE"""),"PT. Top Point Medical") -> PT. Top Point Medical | C55: =IFERROR(__xludf.DUMMYFUNCTION("""COMPUTED_VALUE"""),"Pembelian Pesanan RS Suyoto") -> Pembelian Pesanan RS Suyoto | E55: =IFERROR(__xludf.DUMMYFUNCTION("""COMPUTED_VALUE"""),"Pesanan RS Suyoto") -> Pesanan RS Suyoto | F55: =IFERROR(__xludf.DUMMYFUNCTION("""COMPUTED_VALUE"""),"PO ke TP (Pesanan RS Suyoto)") -> PO ke TP (Pesanan RS Suyoto) | G55: =IFERROR(__xludf.DUMMYFUNCTION("""COMPUTED_VALUE"""),45911.0) -> 45911 | I55: =IFERROR(__xludf.DUMMYFUNCTION("""COMPUTED_VALUE"""),2760901.0) -> 2760901 | J55: =IFERROR(__xludf.DUMMYFUNCTION("""COMPUTED_VALUE"""),303699.0) -> 303699 | L55: =IFERROR(__xludf.DUMMYFUNCTION("""COMPUTED_VALUE"""),3064600.0) -> 3064600 | M55: 45930 | N55: BCA MPG | O55: 3064600 | P55: 45930 | R55: =L55-O55 -> 0
B56: =IFERROR(__xludf.DUMMYFUNCTION("""COMPUTED_VALUE"""),"PT. Whira Pitoe Usaha Bersama") -> PT. Whira Pitoe Usaha Bersama | C56: =IFERROR(__xludf.DUMMYFUNCTION("""COMPUTED_VALUE"""),"Pembelian Biomaxima Biopath (Dinkes Tasikmalaya)") -> Pembelian Biomaxima Biopath (Dinkes Tasikmalaya) | E56: =IFERROR(__xludf.DUMMYFUNCTION("""COMPUTED_VALUE"""),"SP 46 Genta (1).pdf") -> SP 46 Genta (1).pdf | G56: =IFERROR(__xludf.DUMMYFUNCTION("""COMPUTED_VALUE"""),45926.0) -> 45926 | I56: =IFERROR(__xludf.DUMMYFUNCTION("""COMPUTED_VALUE"""),1831351.0) -> 1831351 | J56: =IFERROR(__xludf.DUMMYFUNCTION("""COMPUTED_VALUE"""),201449.0) -> 201449 | L56: =IFERROR(__xludf.DUMMYFUNCTION("""COMPUTED_VALUE"""),2032800.0) -> 2032800 | M56: 45926 | N56: BCA MPG | O56: 2032800 | P56: 45926 | R56: =L56-O56 -> 0
B57: =IFERROR(__xludf.DUMMYFUNCTION("""COMPUTED_VALUE"""),"PT. Sangiang Karya Mandiri") -> PT. Sangiang Karya Mandiri | C57: =IFERROR(__xludf.DUMMYFUNCTION("""COMPUTED_VALUE"""),"Pembelian Egens Combo Diagnostic Kit Multi Drug Panel (Dinkes Tasikmalaya)") -> Pembelian Egens Combo Diagnostic Kit Multi Drug Panel (Dinkes Tasikmalaya) | E57: =IFERROR(__xludf.DUMMYFUNCTION("""COMPUTED_VALUE"""),"SP 46 Genta (1).pdf") -> SP 46 Genta (1).pdf | G57: =IFERROR(__xludf.DUMMYFUNCTION("""COMPUTED_VALUE"""),45925.0) -> 45925 | I57: =IFERROR(__xludf.DUMMYFUNCTION("""COMPUTED_VALUE"""),4375000.0) -> 4375000 | J57: =IFERROR(__xludf.DUMMYFUNCTION("""COMPUTED_VALUE"""),481250.0) -> 481250 | L57: =IFERROR(__xludf.DUMMYFUNCTION("""COMPUTED_VALUE"""),4856250.0) -> 4856250 | M57: 45926 | N57: BCA MPG | O57: 4856250 | P57: 45926 | R57: =L57-O57 -> 0
B58: =IFERROR(__xludf.DUMMYFUNCTION("""COMPUTED_VALUE"""),"PT. BSM") -> PT. BSM | C58: =IFERROR(__xludf.DUMMYFUNCTION("""COMPUTED_VALUE"""),"Pembelian Monetes ") -> Pembelian Monetes | E58: =IFERROR(__xludf.DUMMYFUNCTION("""COMPUTED_VALUE"""),"SP 46 Genta (1).pdf") -> SP 46 Genta (1).pdf | G58: =IFERROR(__xludf.DUMMYFUNCTION("""COMPUTED_VALUE"""),45925.0) -> 45925 | I58: =IFERROR(__xludf.DUMMYFUNCTION("""COMPUTED_VALUE"""),567572.0) -> 567572 | J58: =IFERROR(__xludf.DUMMYFUNCTION("""COMPUTED_VALUE"""),62433.0) -> 62433 | L58: =IFERROR(__xludf.DUMMYFUNCTION("""COMPUTED_VALUE"""),630005.0) -> 630005 | M58: 45926 | N58: BCA MPG | O58: 630005 | P58: 45926 | R58: =L58-O58 -> 0
R59: =L59-O59 -> 0
B60: =IFERROR(__xludf.DUMMYFUNCTION("""COMPUTED_VALUE"""),"Pramuka") -> Pramuka | C60: =IFERROR(__xludf.DUMMYFUNCTION("""COMPUTED_VALUE"""),"Pembelian 70 Box sarung tangan (Pesanan PKM Sentul) ") -> Pembelian 70 Box sarung tangan (Pesanan PKM Sentul) | E60: =IFERROR(__xludf.DUMMYFUNCTION("""COMPUTED_VALUE"""),"BMHP Sentul.pdf") -> BMHP Sentul.pdf | G60: =IFERROR(__xludf.DUMMYFUNCTION("""COMPUTED_VALUE"""),45937.0) -> 45937 | I60: =IFERROR(__xludf.DUMMYFUNCTION("""COMPUTED_VALUE"""),2800000.0) -> 2800000 | L60: =IFERROR(__xludf.DUMMYFUNCTION("""COMPUTED_VALUE"""),2800000.0) -> 2800000 | M60: 45937 | N60: BCA MPG | O60: 2800000 | P60: 45937 | R60: =L60-O60 -> 0
B61: =IFERROR(__xludf.DUMMYFUNCTION("""COMPUTED_VALUE"""),"Shopee") -> Shopee | C61: =IFERROR(__xludf.DUMMYFUNCTION("""COMPUTED_VALUE"""),"Alcohol Swab (PKM SENTUL) 50 Box") -> Alcohol Swab (PKM SENTUL) 50 Box | E61: =IFERROR(__xludf.DUMMYFUNCTION("""COMPUTED_VALUE"""),"BMHP Sentul.pdf") -> BMHP Sentul.pdf | G61: =IFERROR(__xludf.DUMMYFUNCTION("""COMPUTED_VALUE"""),45937.0) -> 45937 | I61: =IFERROR(__xludf.DUMMYFUNCTION("""COMPUTED_VALUE"""),394000.0) -> 394000 | L61: =IFERROR(__xludf.DUMMYFUNCTION("""COMPUTED_VALUE"""),394000.0) -> 394000 | M61: 45937 | N61: BCA MPG | O61: 394000 | P61: 45937 | R61: =L61-O61 -> 0
B62: =IFERROR(__xludf.DUMMYFUNCTION("""COMPUTED_VALUE"""),"Shopee") -> Shopee | C62: =IFERROR(__xludf.DUMMYFUNCTION("""COMPUTED_VALUE"""),"Masker 50 Box (PKM Sentul)") -> Masker 50 Box (PKM Sentul) | E62: =IFERROR(__xludf.DUMMYFUNCTION("""COMPUTED_VALUE"""),"BMHP Sentul.pdf") -> BMHP Sentul.pdf | G62: =IFERROR(__xludf.DUMMYFUNCTION("""COMPUTED_VALUE"""),45937.0) -> 45937 | I62: =IFERROR(__xludf.DUMMYFUNCTION("""COMPUTED_VALUE"""),527800.0) -> 527800 | L62: =IFERROR(__xludf.DUMMYFUNCTION("""COMPUTED_VALUE"""),527800.0) -> 527800 | M62: 45937 | N62: BCA MPG | O62: 527800 | P62: 45937 | R62: =L62-O62 -> 0
B63: =IFERROR(__xludf.DUMMYFUNCTION("""COMPUTED_VALUE"""),"Top Point") -> Top Point | C63: =IFERROR(__xludf.DUMMYFUNCTION("""COMPUTED_VALUE"""),"Pembelian Spuit 3cc") -> Pembelian Spuit 3cc | E63: =IFERROR(__xludf.DUMMYFUNCTION("""COMPUTED_VALUE"""),"BMHP Sentul.pdf") -> BMHP Sentul.pdf | F63: =IFERROR(__xludf.DUMMYFUNCTION("""COMPUTED_VALUE"""),"MPG-021025003 - Top Point (PKM Sentul).pdf") -> MPG-021025003 - Top Point (PKM Sentul).pdf | G63: =IFERROR(__xludf.DUMMYFUNCTION("""COMPUTED_VALUE"""),45936.0) -> 45936 | I63: =IFERROR(__xludf.DUMMYFUNCTION("""COMPUTED_VALUE"""),1091992.0) -> 1091992 | J63: =IFERROR(__xludf.DUMMYFUNCTION("""COMPUTED_VALUE"""),120119.0) -> 120119 | L63: =IFERROR(__xludf.DUMMYFUNCTION("""COMPUTED_VALUE"""),1212111.0) -> 1212111 | M63: 45967 | N63: BCA MPG | O63: =L63 -> 1212111 | P63: =M63 -> 45967 | R63: =L63-O63 -> 0
B64: =IFERROR(__xludf.DUMMYFUNCTION("""COMPUTED_VALUE"""),"BSM") -> BSM | C64: =IFERROR(__xludf.DUMMYFUNCTION("""COMPUTED_VALUE"""),"Pembelian Tabung Plan Merah, Stik Asam Urat, Stik Kolestrol, EDTA 3ML (PKM CIAWI)") -> Pembelian Tabung Plan Merah, Stik Asam Urat, Stik Kolestrol, EDTA 3ML (PKM CIAWI) | E64: =IFERROR(__xludf.DUMMYFUNCTION("""COMPUTED_VALUE"""),"surat-pesanan-EP-01K6M1B6X4Q02429HWGQBC58JY PKM CIAWI.pdf") -> surat-pesanan-EP-01K6M1B6X4Q02429HWGQBC58JY PKM CIAWI.pdf | F64: =IFERROR(__xludf.DUMMYFUNCTION("""COMPUTED_VALUE"""),"MPG-031025005 - PT. BSM ...pdf") -> MPG-031025005 - PT. BSM ...pdf | G64: =IFERROR(__xludf.DUMMYFUNCTION("""COMPUTED_VALUE"""),45937.0) -> 45937 | I64: =IFERROR(__xludf.DUMMYFUNCTION("""COMPUTED_VALUE"""),7005554.0) -> 7005554 | L64: =IFERROR(__xludf.DUMMYFUNCTION("""COMPUTED_VALUE"""),7005554.0) -> 7005554 | M64: 45937 | N64: BCA MPG | O64: 7005554 | P64: 45937 | R64: =L64-O64 -> 0
B65: =IFERROR(__xludf.DUMMYFUNCTION("""COMPUTED_VALUE"""),"shopee") -> shopee | C65: =IFERROR(__xludf.DUMMYFUNCTION("""COMPUTED_VALUE"""),"Pembelian Yellow Tip (PKM CIAWI)") -> Pembelian Yellow Tip (PKM CIAWI) | E65: =IFERROR(__xludf.DUMMYFUNCTION("""COMPUTED_VALUE"""),"surat-pesanan-EP-01K6M1B6X4Q02429HWGQBC58JY PKM CIAWI.pdf") -> surat-pesanan-EP-01K6M1B6X4Q02429HWGQBC58JY PKM CIAWI.pdf | G65: =IFERROR(__xludf.DUMMYFUNCTION("""COMPUTED_VALUE"""),45937.0) -> 45937 | I65: =IFERROR(__xludf.DUMMYFUNCTION("""COMPUTED_VALUE"""),79108.0) -> 79108 | L65: =IFERROR(__xludf.DUMMYFUNCTION("""COMPUTED_VALUE"""),79108.0) -> 79108 | M65: 45937 | N65: BCA MPG | O65: 79108 | P65: 45937 | R65: =L65-O65 -> 0
B66: =IFERROR(__xludf.DUMMYFUNCTION("""COMPUTED_VALUE"""),"shopee") -> shopee | C66: =IFERROR(__xludf.DUMMYFUNCTION("""COMPUTED_VALUE"""),"Pembelian Kartu Goldar (PKM CIAWI)") -> Pembelian Kartu Goldar (PKM CIAWI) | E66: =IFERROR(__xludf.DUMMYFUNCTION("""COMPUTED_VALUE"""),"surat-pesanan-EP-01K6M1B6X4Q02429HWGQBC58JY PKM CIAWI.pdf") -> surat-pesanan-EP-01K6M1B6X4Q02429HWGQBC58JY PKM CIAWI.pdf | G66: =IFERROR(__xludf.DUMMYFUNCTION("""COMPUTED_VALUE"""),45937.0) -> 45937 | I66: =IFERROR(__xludf.DUMMYFUNCTION("""COMPUTED_VALUE"""),66990.0) -> 66990 | L66: =IFERROR(__xludf.DUMMYFUNCTION("""COMPUTED_VALUE"""),66990.0) -> 66990 | M66: 45937 | N66: BCA MPG | O66: 66990 | P66: 45937 | R66: =L66-O66 -> 0
B67: =IFERROR(__xludf.DUMMYFUNCTION("""COMPUTED_VALUE"""),"shopee") -> shopee | C67: =IFERROR(__xludf.DUMMYFUNCTION("""COMPUTED_VALUE"""),"Pembelian Pot Urine (PKM CIAWI)") -> Pembelian Pot Urine (PKM CIAWI) | E67: =IFERROR(__xludf.DUMMYFUNCTION("""COMPUTED_VALUE"""),"surat-pesanan-EP-01K6M1B6X4Q02429HWGQBC58JY PKM CIAWI.pdf") -> surat-pesanan-EP-01K6M1B6X4Q02429HWGQBC58JY PKM CIAWI.pdf | G67: =IFERROR(__xludf.DUMMYFUNCTION("""COMPUTED_VALUE"""),45937.0) -> 45937 | I67: =IFERROR(__xludf.DUMMYFUNCTION("""COMPUTED_VALUE"""),476400.0) -> 476400 | L67: =IFERROR(__xludf.DUMMYFUNCTION("""COMPUTED_VALUE"""),476400.0) -> 476400 | M67: 45937 | N67: BCA MPG | O67: 476400 | P67: 45937 | R67: =L67-O67 -> 0
C68: =IFERROR(__xludf.DUMMYFUNCTION("""COMPUTED_VALUE"""),"Cashback pkm cihideng udik2, cogrek,cangkurawok") -> Cashback pkm cihideng udik2, cogrek,cangkurawok | G68: =IFERROR(__xludf.DUMMYFUNCTION("""COMPUTED_VALUE"""),45937.0) -> 45937 | I68: =IFERROR(__xludf.DUMMYFUNCTION("""COMPUTED_VALUE"""),1788970.29) -> 1788970.3 | L68: =IFERROR(__xludf.DUMMYFUNCTION("""COMPUTED_VALUE"""),1788970.29) -> 1788970.3 | M68: 45937 | N68: BCA MPG | O68: 1788970 | P68: 45937 | R68: =L68-O68 -> 0.29
B69: =IFERROR(__xludf.DUMMYFUNCTION("""COMPUTED_VALUE"""),"PT. Wira Pithoe") -> PT. Wira Pithoe | C69: =IFERROR(__xludf.DUMMYFUNCTION("""COMPUTED_VALUE"""),"Pembelian Reagen Cholestrol (Dinkes Tasik)") -> Pembelian Reagen Cholestrol (Dinkes Tasik) | E69: =IFERROR(__xludf.DUMMYFUNCTION("""COMPUTED_VALUE"""),"SP Dinkes Tasikmalaya") -> SP Dinkes Tasikmalaya | G69: =IFERROR(__xludf.DUMMYFUNCTION("""COMPUTED_VALUE"""),45940.0) -> 45940 | I69: =IFERROR(__xludf.DUMMYFUNCTION("""COMPUTED_VALUE"""),840000.0) -> 840000 | J69: =IFERROR(__xludf.DUMMYFUNCTION("""COMPUTED_VALUE"""),92400.0) -> 92400 | L69: =IFERROR(__xludf.DUMMYFUNCTION("""COMPUTED_VALUE"""),932400.0) -> 932400 | M69: 45940 | N69: BCA MPG | O69: 932400 | P69: 45940 | R69: =L69-O69 -> 0
B70: =IFERROR(__xludf.DUMMYFUNCTION("""COMPUTED_VALUE"""),"PT. BSM") -> PT. BSM | C70: =IFERROR(__xludf.DUMMYFUNCTION("""COMPUTED_VALUE"""),"Pembelian Edta (Dinkes Tasik) dan untuk stock") -> Pembelian Edta (Dinkes Tasik) dan untuk stock | E70: =IFERROR(__xludf.DUMMYFUNCTION("""COMPUTED_VALUE"""),"SP Dinkes Tasikmalaya") -> SP Dinkes Tasikmalaya | F70: =IFERROR(__xludf.DUMMYFUNCTION("""COMPUTED_VALUE"""),"PO - BSM (dinkes tasik).pdf") -> PO - BSM (dinkes tasik).pdf | G70: =IFERROR(__xludf.DUMMYFUNCTION("""COMPUTED_VALUE"""),45938.0) -> 45938 | I70: =IFERROR(__xludf.DUMMYFUNCTION("""COMPUTED_VALUE"""),306304.0) -> 306304 | J70: =IFERROR(__xludf.DUMMYFUNCTION("""COMPUTED_VALUE"""),33693.0) -> 33693 | L70: =IFERROR(__xludf.DUMMYFUNCTION("""COMPUTED_VALUE"""),339997.0) -> 339997 | M70: 45938 | N70: BCA MPG | O70: 339997 | P70: 45938 | R70: =L70-O70 -> 0
B71: =IFERROR(__xludf.DUMMYFUNCTION("""COMPUTED_VALUE"""),"Shopee") -> Shopee | C71: =IFERROR(__xludf.DUMMYFUNCTION("""COMPUTED_VALUE"""),"Cover glass (Dinkes Tasik)") -> Cover glass (Dinkes Tasik) | E71: =IFERROR(__xludf.DUMMYFUNCTION("""COMPUTED_VALUE"""),"SP Dinkes Tasikmalaya") -> SP Dinkes Tasikmalaya | G71: =IFERROR(__xludf.DUMMYFUNCTION("""COMPUTED_VALUE"""),45938.0) -> 45938 | I71: =IFERROR(__xludf.DUMMYFUNCTION("""COMPUTED_VALUE"""),21500.0) -> 21500 | L71: =IFERROR(__xludf.DUMMYFUNCTION("""COMPUTED_VALUE"""),21500.0) -> 21500 | M71: 45938 | N71: BCA MPG | O71: 21500 | P71: 45938 | R71: =L71-O71 -> 0
B72: =IFERROR(__xludf.DUMMYFUNCTION("""COMPUTED_VALUE"""),"PT. Biosensor") -> PT. Biosensor | C72: =IFERROR(__xludf.DUMMYFUNCTION("""COMPUTED_VALUE"""),"Pembelian Stik Codefree (PKM CIAWI)") -> Pembelian Stik Codefree (PKM CIAWI) | E72: =IFERROR(__xludf.DUMMYFUNCTION("""COMPUTED_VALUE"""),"surat-pesanan-EP-01K6M1B6X4Q02429HWGQBC58JY PKM CIAWI.pdf") -> surat-pesanan-EP-01K6M1B6X4Q02429HWGQBC58JY PKM CIAWI.pdf | F72: =IFERROR(__xludf.DUMMYFUNCTION("""COMPUTED_VALUE"""),"MPG-031025004 - PO BIOSENSOR.pdf") -> MPG-031025004 - PO BIOSENSOR.pdf | G72: =IFERROR(__xludf.DUMMYFUNCTION("""COMPUTED_VALUE"""),45940.0) -> 45940 | I72: =IFERROR(__xludf.DUMMYFUNCTION("""COMPUTED_VALUE"""),1340090.0) -> 1340090 | J72: =IFERROR(__xludf.DUMMYFUNCTION("""COMPUTED_VALUE"""),147409.0) -> 147409 | L72: =IFERROR(__xludf.DUMMYFUNCTION("""COMPUTED_VALUE"""),1487499.0) -> 1487499 | M72: 45940 | N72: BCA MPG | O72: 1487499 | P72: 45940 | R72: =L72-O72 -> 0
C73: =IFERROR(__xludf.DUMMYFUNCTION("""COMPUTED_VALUE"""),"Cashback PKM Kelapa 2") -> Cashback PKM Kelapa 2 | E73: =IFERROR(__xludf.DUMMYFUNCTION("""COMPUTED_VALUE"""),"SP Belanja Kebersihan Puskesmas Kelapa Dua September 2025.pdf") -> SP Belanja Kebersihan Puskesmas Kelapa Dua September 2025.pdf | G73: =IFERROR(__xludf.DUMMYFUNCTION("""COMPUTED_VALUE"""),45938.0) -> 45938 | I73: =IFERROR(__xludf.DUMMYFUNCTION("""COMPUTED_VALUE"""),1451916.0) -> 1451916 | L73: =IFERROR(__xludf.DUMMYFUNCTION("""COMPUTED_VALUE"""),1451916.0) -> 1451916 | M73: 45938 | N73: BCA MPG | O73: 1451916 | P73: 45938 | R73: =L73-O73 -> 0
B74: =IFERROR(__xludf.DUMMYFUNCTION("""COMPUTED_VALUE"""),"PT. Klipindo Plastik Pratama") -> PT. Klipindo Plastik Pratama | C74: =IFERROR(__xludf.DUMMYFUNCTION("""COMPUTED_VALUE"""),"Pesanan Plastik (RSUD Ps.Minggu) 1.000 Pack dan pkm sentul 300 pack") -> Pesanan Plastik (RSUD Ps.Minggu) 1.000 Pack dan pkm sentul 300 pack | E74: =IFERROR(__xludf.DUMMYFUNCTION("""COMPUTED_VALUE"""),"Rsud Pasar Minggu.pdf") -> Rsud Pasar Minggu.pdf | F74: =IFERROR(__xludf.DUMMYFUNCTION("""COMPUTED_VALUE"""),"MPG-101025010 - PT. Klipindo Plastik Pratama.pdf") -> MPG-101025010 - PT. Klipindo Plastik Pratama.pdf | G74: =IFERROR(__xludf.DUMMYFUNCTION("""COMPUTED_VALUE"""),45940.0) -> 45940 | I74: =IFERROR(__xludf.DUMMYFUNCTION("""COMPUTED_VALUE"""),1.15259E7) -> 11525900 | L74: =IFERROR(__xludf.DUMMYFUNCTION("""COMPUTED_VALUE"""),1.15259E7) -> 11525900 | M74: 45943 | N74: BCA MPG | O74: 11525900 | P74: 45943 | R74: =L74-O74 -> 0
B75: =IFERROR(__xludf.DUMMYFUNCTION("""COMPUTED_VALUE"""),"Shopee") -> Shopee | C75: =IFERROR(__xludf.DUMMYFUNCTION("""COMPUTED_VALUE"""),"Pembelian Pesanan APAR 3.5 KG (PKM Bojong)") -> Pembelian Pesanan APAR 3.5 KG (PKM Bojong) | E75: =IFERROR(__xludf.DUMMYFUNCTION("""COMPUTED_VALUE"""),"surat-pesanan-EP-01K6M7R46NK0HCYZ9GCCRKJKVV Pkm Bojong.pdf") -> surat-pesanan-EP-01K6M7R46NK0HCYZ9GCCRKJKVV Pkm Bojong.pdf | G75: =IFERROR(__xludf.DUMMYFUNCTION("""COMPUTED_VALUE"""),45940.0) -> 45940 | I75: =IFERROR(__xludf.DUMMYFUNCTION("""COMPUTED_VALUE"""),876000.0) -> 876000 | L75: =IFERROR(__xludf.DUMMYFUNCTION("""COMPUTED_VALUE"""),876000.0) -> 876000 | M75: 45940 | N75: BCA MPG | O75: 876000 | P75: 45940 | R75: =L75-O75 -> 0
B76: =IFERROR(__xludf.DUMMYFUNCTION("""COMPUTED_VALUE"""),"PT. Top Point") -> PT. Top Point | C76: =IFERROR(__xludf.DUMMYFUNCTION("""COMPUTED_VALUE"""),"Pembelian Feeding Tube (RSUD DR. ADJIDARMO)") -> Pembelian Feeding Tube (RSUD DR. ADJIDARMO) | E76: =IFERROR(__xludf.DUMMYFUNCTION("""COMPUTED_VALUE"""),"SP RSUD Adjidarmo.pdf") -> SP RSUD Adjidarmo.pdf | F76: =IFERROR(__xludf.DUMMYFUNCTION("""COMPUTED_VALUE"""),"MPG-081025007 - Top Point (Feeding Tube).pdf") -> MPG-081025007 - Top Point (Feeding Tube).pdf | H76: =IFERROR(__xludf.DUMMYFUNCTION("""COMPUTED_VALUE"""),"Tempo") -> Tempo | I76: =IFERROR(__xludf.DUMMYFUNCTION("""COMPUTED_VALUE"""),5929000.0) -> 5929000 | L76: =IFERROR(__xludf.DUMMYFUNCTION("""COMPUTED_VALUE"""),5929000.0) -> 5929000 | N76: BCA MPG | R76: =L76-O76 -> 5929000 | U76: blm dibyr\
B77: =IFERROR(__xludf.DUMMYFUNCTION("""COMPUTED_VALUE"""),"PT Wira Pithoe") -> PT Wira Pithoe | C77: =IFERROR(__xludf.DUMMYFUNCTION("""COMPUTED_VALUE"""),"Pesanan Dinkes Tasik (koletsrol,trigiliserida,sgot,sgpt,ureum,kreatinin)") -> Pesanan Dinkes Tasik (koletsrol,trigiliserida,sgot,sgpt,ureum,kreatinin) | E77: =IFERROR(__xludf.DUMMYFUNCTION("""COMPUTED_VALUE"""),"Surat Pesanan Dinkes Tasikmalaya") -> Surat Pesanan Dinkes Tasikmalaya | F77: =IFERROR(__xludf.DUMMYFUNCTION("""COMPUTED_VALUE"""),"MPG-131025012 - PT WIRA PITHOE (dinkes tasik).pdf") -> MPG-131025012 - PT WIRA PITHOE (dinkes tasik).pdf | G77: =IFERROR(__xludf.DUMMYFUNCTION("""COMPUTED_VALUE"""),45943.0) -> 45943 | I77: =IFERROR(__xludf.DUMMYFUNCTION("""COMPUTED_VALUE"""),1.0074E7) -> 10074000 | J77: =IFERROR(__xludf.DUMMYFUNCTION("""COMPUTED_VALUE"""),1108140.0) -> 1108140 | L77: =IFERROR(__xludf.DUMMYFUNCTION("""COMPUTED_VALUE"""),1.118214E7) -> 11182140 | M77: 45943 | N77: BCA MPG | O77: 11182140 | P77: 45943 | R77: =L77-O77 -> 0
B78: =IFERROR(__xludf.DUMMYFUNCTION("""COMPUTED_VALUE"""),"PT. Dhyas Mitra Usaha") -> PT. Dhyas Mitra Usaha | C78: =IFERROR(__xludf.DUMMYFUNCTION("""COMPUTED_VALUE"""),"Pesanan Dinkes Tasik (Pot urine, Alcohol swab, sarung tangan s/m)") -> Pesanan Dinkes Tasik (Pot urine, Alcohol swab, sarung tangan s/m) | E78: =IFERROR(__xludf.DUMMYFUNCTION("""COMPUTED_VALUE"""),"Surat Pesanan Dinkes Tasikmalaya") -> Surat Pesanan Dinkes Tasikmalaya | F78: =IFERROR(__xludf.DUMMYFUNCTION("""COMPUTED_VALUE"""),"MPG-131025013 - PT. DHYAS (Dinkes Tasikmalaya).pdf") -> MPG-131025013 - PT. DHYAS (Dinkes Tasikmalaya).pdf | G78: =IFERROR(__xludf.DUMMYFUNCTION("""COMPUTED_VALUE"""),45943.0) -> 45943 | I78: =IFERROR(__xludf.DUMMYFUNCTION("""COMPUTED_VALUE"""),1994600.0) -> 1994600 | L78: =IFERROR(__xludf.DUMMYFUNCTION("""COMPUTED_VALUE"""),1994600.0) -> 1994600 | M78: 45943 | N78: BCA MPG | O78: 1994600 | P78: 45943 | R78: =L78-O78 -> 0
B79: =IFERROR(__xludf.DUMMYFUNCTION("""COMPUTED_VALUE"""),"PT. SGM") -> PT. SGM | C79: =IFERROR(__xludf.DUMMYFUNCTION("""COMPUTED_VALUE"""),"Pesanan Dinkes Tasik (Goldar Set)") -> Pesanan Dinkes Tasik (Goldar Set) | E79: =IFERROR(__xludf.DUMMYFUNCTION("""COMPUTED_VALUE"""),"Surat Pesanan Dinkes Tasikmalaya") -> Surat Pesanan Dinkes Tasikmalaya | F79: =IFERROR(__xludf.DUMMYFUNCTION("""COMPUTED_VALUE"""),"MPG-131025015 - PT.SGM.pdf") -> MPG-131025015 - PT.SGM.pdf | G79: =IFERROR(__xludf.DUMMYFUNCTION("""COMPUTED_VALUE"""),45943.0) -> 45943 | I79: =IFERROR(__xludf.DUMMYFUNCTION("""COMPUTED_VALUE"""),652000.0) -> 652000 | J79: =IFERROR(__xludf.DUMMYFUNCTION("""COMPUTED_VALUE"""),71720.0) -> 71720 | L79: =IFERROR(__xludf.DUMMYFUNCTION("""COMPUTED_VALUE"""),723720.0) -> 723720 | M79: 45943 | N79: BCA MPG | O79: 723720 | P79: 45943 | R79: =L79-O79 -> 0
B80: =IFERROR(__xludf.DUMMYFUNCTION("""COMPUTED_VALUE"""),"PT. BSM") -> PT. BSM | C80: =IFERROR(__xludf.DUMMYFUNCTION("""COMPUTED_VALUE"""),"Pesanan Dinkes Tasik (Tes kehamilan,tabung edta,tabung gel,yellow white tip,urine p,led)") -> Pesanan Dinkes Tasik (Tes kehamilan,tabung edta,tabung gel,yellow white tip,urine p,led) | E80: =IFERROR(__xludf.DUMMYFUNCTION("""COMPUTED_VALUE"""),"Surat Pesanan Dinkes Tasikmalaya") -> Surat Pesanan Dinkes Tasikmalaya | F80: =IFERROR(__xludf.DUMMYFUNCTION("""COMPUTED_VALUE"""),"MPG-131025014 -BSM (Dinkes Tasik).pdf") -> MPG-131025014 -BSM (Dinkes Tasik).pdf | G80: =IFERROR(__xludf.DUMMYFUNCTION("""COMPUTED_VALUE"""),45943.0) -> 45943 | I80: =IFERROR(__xludf.DUMMYFUNCTION("""COMPUTED_VALUE"""),5634862.0) -> 5634862 | J80: =IFERROR(__xludf.DUMMYFUNCTION("""COMPUTED_VALUE"""),619835.0) -> 619835 | L80: =IFERROR(__xludf.DUMMYFUNCTION("""COMPUTED_VALUE"""),6254697.0) -> 6254697 | M80: 45943 | N80: BCA MPG | O80: 6254697 | P80: 45943 | R80: =L80-O80 -> 0
B81: =IFERROR(__xludf.DUMMYFUNCTION("""COMPUTED_VALUE"""),"shopee") -> shopee | C81: =IFERROR(__xludf.DUMMYFUNCTION("""COMPUTED_VALUE"""),"Pesanan Dinkes Tasik (Kartu Goldar)") -> Pesanan Dinkes Tasik (Kartu Goldar) | E81: =IFERROR(__xludf.DUMMYFUNCTION("""COMPUTED_VALUE"""),"Surat Pesanan Dinkes Tasikmalaya") -> Surat Pesanan Dinkes Tasikmalaya | G81: =IFERROR(__xludf.DUMMYFUNCTION("""COMPUTED_VALUE"""),45943.0) -> 45943 | I81: =IFERROR(__xludf.DUMMYFUNCTION("""COMPUTED_VALUE"""),80500.0) -> 80500 | L81: =IFERROR(__xludf.DUMMYFUNCTION("""COMPUTED_VALUE"""),80500.0) -> 80500 | M81: 45943 | N81: BCA MPG | O81: 80500 | P81: 45943 | R81: =L81-O81 -> 0
B82: =IFERROR(__xludf.DUMMYFUNCTION("""COMPUTED_VALUE"""),"shopee") -> shopee | C82: =IFERROR(__xludf.DUMMYFUNCTION("""COMPUTED_VALUE"""),"Pesanan Dinkes Tasik (Rak Tabung)") -> Pesanan Dinkes Tasik (Rak Tabung) | E82: =IFERROR(__xludf.DUMMYFUNCTION("""COMPUTED_VALUE"""),"Surat Pesanan Dinkes Tasikmalaya") -> Surat Pesanan Dinkes Tasikmalaya | G82: =IFERROR(__xludf.DUMMYFUNCTION("""COMPUTED_VALUE"""),45943.0) -> 45943 | I82: =IFERROR(__xludf.DUMMYFUNCTION("""COMPUTED_VALUE"""),676420.0) -> 676420 | L82: =IFERROR(__xludf.DUMMYFUNCTION("""COMPUTED_VALUE"""),676420.0) -> 676420 | M82: 45943 | N82: BCA MPG | O82: 676420 | P82: 45943 | R82: =L82-O82 -> 0
B83: =IFERROR(__xludf.DUMMYFUNCTION("""COMPUTED_VALUE"""),"shopee") -> shopee | C83: =IFERROR(__xludf.DUMMYFUNCTION("""COMPUTED_VALUE"""),"Pesanan Dinkes Tasik ( Tourniquet)") -> Pesanan Dinkes Tasik ( Tourniquet) | E83: =IFERROR(__xludf.DUMMYFUNCTION("""COMPUTED_VALUE"""),"Surat Pesanan Dinkes Tasikmalaya") -> Surat Pesanan Dinkes Tasikmalaya | G83: =IFERROR(__xludf.DUMMYFUNCTION("""COMPUTED_VALUE"""),45943.0) -> 45943 | I83: =IFERROR(__xludf.DUMMYFUNCTION("""COMPUTED_VALUE"""),32070.0) -> 32070 | L83: =IFERROR(__xludf.DUMMYFUNCTION("""COMPUTED_VALUE"""),32070.0) -> 32070 | M83: 45943 | N83: BCA MPG | O83: 32070 | P83: 45943 | R83: =L83-O83 -> 0
B84: =IFERROR(__xludf.DUMMYFUNCTION("""COMPUTED_VALUE"""),"shopee") -> shopee | C84: =IFERROR(__xludf.DUMMYFUNCTION("""COMPUTED_VALUE"""),"Pesanan Dinkes Tasik (Okplast)") -> Pesanan Dinkes Tasik (Okplast) | E84: =IFERROR(__xludf.DUMMYFUNCTION("""COMPUTED_VALUE"""),"Surat Pesanan Dinkes Tasikmalaya") -> Surat Pesanan Dinkes Tasikmalaya | G84: =IFERROR(__xludf.DUMMYFUNCTION("""COMPUTED_VALUE"""),45943.0) -> 45943 | I84: =IFERROR(__xludf.DUMMYFUNCTION("""COMPUTED_VALUE"""),218500.0) -> 218500 | L84: =IFERROR(__xludf.DUMMYFUNCTION("""COMPUTED_VALUE"""),218500.0) -> 218500 | M84: 45943 | N84: BCA MPG | O84: 218500 | P84: 45943 | R84: =L84-O84 -> 0
B85: =IFERROR(__xludf.DUMMYFUNCTION("""COMPUTED_VALUE"""),"shopee") -> shopee | C85: =IFERROR(__xludf.DUMMYFUNCTION("""COMPUTED_VALUE"""),"Pesanan Dinkes Tasik (Masker)") -> Pesanan Dinkes Tasik (Masker) | E85: =IFERROR(__xludf.DUMMYFUNCTION("""COMPUTED_VALUE"""),"Surat Pesanan Dinkes Tasikmalaya") -> Surat Pesanan Dinkes Tasikmalaya | G85: =IFERROR(__xludf.DUMMYFUNCTION("""COMPUTED_VALUE"""),45943.0) -> 45943 | I85: =IFERROR(__xludf.DUMMYFUNCTION("""COMPUTED_VALUE"""),81940.0) -> 81940 | L85: =IFERROR(__xludf.DUMMYFUNCTION("""COMPUTED_VALUE"""),81940.0) -> 81940 | M85: 45943 | N85: BCA MPG | O85: 81940 | P85: 45943 | R85: =L85-O85 -> 0
B86: =IFERROR(__xludf.DUMMYFUNCTION("""COMPUTED_VALUE"""),"PT.Top Point") -> PT.Top Point | C86: =IFERROR(__xludf.DUMMYFUNCTION("""COMPUTED_VALUE"""),"Pesanan RSPP ") -> Pesanan RSPP | E86: =IFERROR(__xludf.DUMMYFUNCTION("""COMPUTED_VALUE"""),"po rspp (6)") -> po rspp (6) | F86: =IFERROR(__xludf.DUMMYFUNCTION("""COMPUTED_VALUE"""),"MPG-011025001 - TOP POINT (Pesanan RSPP) ..pdf") -> MPG-011025001 - TOP POINT (Pesanan RSPP) ..pdf | G86: =IFERROR(__xludf.DUMMYFUNCTION("""COMPUTED_VALUE"""),45931.0) -> 45931 | H86: =IFERROR(__xludf.DUMMYFUNCTION("""COMPUTED_VALUE"""),"tempo") -> tempo | I86: =IFERROR(__xludf.DUMMYFUNCTION("""COMPUTED_VALUE"""),3800676.0) -> 3800676 | J86: =IFERROR(__xludf.DUMMYFUNCTION("""COMPUTED_VALUE"""),418074.0) -> 418074 | L86: =IFERROR(__xludf.DUMMYFUNCTION("""COMPUTED_VALUE"""),4218750.0) -> 4218750 | M86: 45967 | N86: BCA MPG | O86: 4218750 | P86: 45967 | R86: =L86-O86 -> 0
B87: =IFERROR(__xludf.DUMMYFUNCTION("""COMPUTED_VALUE"""),"PT. Tirta Investama") -> PT. Tirta Investama | C87: =IFERROR(__xludf.DUMMYFUNCTION("""COMPUTED_VALUE"""),"Galon Kantor (Pemakaian September)") -> Galon Kantor (Pemakaian September) | I87: =IFERROR(__xludf.DUMMYFUNCTION("""COMPUTED_VALUE"""),679999.0) -> 679999 | L87: =IFERROR(__xludf.DUMMYFUNCTION("""COMPUTED_VALUE"""),679999.0) -> 679999 | M87: 45943 | N87: BCA MPG | O87: 679999 | P87: 45943 | R87: =L87-O87 -> 0
B88: =IFERROR(__xludf.DUMMYFUNCTION("""COMPUTED_VALUE"""),"PT. BSM") -> PT. BSM | C88: =IFERROR(__xludf.DUMMYFUNCTION("""COMPUTED_VALUE"""),"Pesanan Tambahan (Dinkes Tasik) Safety Box") -> Pesanan Tambahan (Dinkes Tasik) Safety Box | E88: =IFERROR(__xludf.DUMMYFUNCTION("""COMPUTED_VALUE"""),"SP 53 mata pensil susulan add.jpg") -> SP 53 mata pensil susulan add.jpg | F88: =IFERROR(__xludf.DUMMYFUNCTION("""COMPUTED_VALUE"""),"MPG-141025016 - PT. BSM (Safety Box).pdf") -> MPG-141025016 - PT. BSM (Safety Box).pdf | G88: =IFERROR(__xludf.DUMMYFUNCTION("""COMPUTED_VALUE"""),45944.0) -> 45944 | I88: =IFERROR(__xludf.DUMMYFUNCTION("""COMPUTED_VALUE"""),612640.0) -> 612640 | J88: =IFERROR(__xludf.DUMMYFUNCTION("""COMPUTED_VALUE"""),67390.0) -> 67390 | L88: =IFERROR(__xludf.DUMMYFUNCTION("""COMPUTED_VALUE"""),680030.0) -> 680030 | M88: 45944 | N88: BCA MPG | O88: 680030 | P88: 45944 | R88: =L88-O88 -> 0
B89: =IFERROR(__xludf.DUMMYFUNCTION("""COMPUTED_VALUE"""),"PT Bintang Setya Media") -> PT Bintang Setya Media | C89: =IFERROR(__xludf.DUMMYFUNCTION("""COMPUTED_VALUE"""),"Pembelian Tinta Printer") -> Pembelian Tinta Printer | G89: =IFERROR(__xludf.DUMMYFUNCTION("""COMPUTED_VALUE"""),45939.0) -> 45939 | I89: =IFERROR(__xludf.DUMMYFUNCTION("""COMPUTED_VALUE"""),1000000.0) -> 1000000 | L89: =IFERROR(__xludf.DUMMYFUNCTION("""COMPUTED_VALUE"""),1000000.0) -> 1000000 | M89: 45944 | N89: BCA MPG | O89: 1000000 | P89: 45944 | R89: =L89-O89 -> 0
B90: =IFERROR(__xludf.DUMMYFUNCTION("""COMPUTED_VALUE"""),"PT Bintang Setya Media") -> PT Bintang Setya Media | C90: =IFERROR(__xludf.DUMMYFUNCTION("""COMPUTED_VALUE"""),"Pembelian Tinta Printer") -> Pembelian Tinta Printer | G90: =IFERROR(__xludf.DUMMYFUNCTION("""COMPUTED_VALUE"""),45943.0) -> 45943 | I90: =IFERROR(__xludf.DUMMYFUNCTION("""COMPUTED_VALUE"""),360000.0) -> 360000 | L90: =IFERROR(__xludf.DUMMYFUNCTION("""COMPUTED_VALUE"""),360000.0) -> 360000 | M90: 45944 | N90: BCA MPG | O90: 360000 | P90: 45944 | R90: =L90-O90 -> 0
B91: =IFERROR(__xludf.DUMMYFUNCTION("""COMPUTED_VALUE"""),"PT. BSM") -> PT. BSM | C91: =IFERROR(__xludf.DUMMYFUNCTION("""COMPUTED_VALUE"""),"Pembelian Deckglass (Dinkes Tasik)") -> Pembelian Deckglass (Dinkes Tasik) | E91: =IFERROR(__xludf.DUMMYFUNCTION("""COMPUTED_VALUE"""),"SP Dinkes Tasikmalaya") -> SP Dinkes Tasikmalaya | F91: =IFERROR(__xludf.DUMMYFUNCTION("""COMPUTED_VALUE"""),"MPG-141025017 - PT BSM (deckglass).pdf") -> MPG-141025017 - PT BSM (deckglass).pdf | G91: =IFERROR(__xludf.DUMMYFUNCTION("""COMPUTED_VALUE"""),45944.0) -> 45944 | I91: =IFERROR(__xludf.DUMMYFUNCTION("""COMPUTED_VALUE"""),720721.0) -> 720721 | J91: =IFERROR(__xludf.DUMMYFUNCTION("""COMPUTED_VALUE"""),79279.0) -> 79279 | L91: =IFERROR(__xludf.DUMMYFUNCTION("""COMPUTED_VALUE"""),800000.0) -> 800000 | M91: 45944 | N91: BCA MPG | O91: 800000 | P91: 45944 | R91: =L91-O91 -> 0
C92: =IFERROR(__xludf.DUMMYFUNCTION("""COMPUTED_VALUE"""),"Listrik dan Parkir Gedung ") -> Listrik dan Parkir Gedung | G92: =IFERROR(__xludf.DUMMYFUNCTION("""COMPUTED_VALUE"""),45945.0) -> 45945 | I92: =IFERROR(__xludf.DUMMYFUNCTION("""COMPUTED_VALUE"""),5710589.0) -> 5710589 | L92: =IFERROR(__xludf.DUMMYFUNCTION("""COMPUTED_VALUE"""),5710589.0) -> 5710589 | M92: 45945 | N92: BCA MPG | O92: 5710589 | P92: 45945 | R92: =L92-O92 -> 0
C93: =IFERROR(__xludf.DUMMYFUNCTION("""COMPUTED_VALUE"""),"Pengajuan dinas tasik pa agus") -> Pengajuan dinas tasik pa agus | G93: =IFERROR(__xludf.DUMMYFUNCTION("""COMPUTED_VALUE"""),45945.0) -> 45945 | I93: =IFERROR(__xludf.DUMMYFUNCTION("""COMPUTED_VALUE"""),1000000.0) -> 1000000 | L93: =IFERROR(__xludf.DUMMYFUNCTION("""COMPUTED_VALUE"""),1000000.0) -> 1000000 | M93: 45945 | N93: BCA MPG | O93: 1000000 | P93: 45945 | R93: =L93-O93 -> 0
C94: =IFERROR(__xludf.DUMMYFUNCTION("""COMPUTED_VALUE"""),"Pembayaran CDAKB") -> Pembayaran CDAKB | G94: =IFERROR(__xludf.DUMMYFUNCTION("""COMPUTED_VALUE"""),45945.0) -> 45945 | I94: =IFERROR(__xludf.DUMMYFUNCTION("""COMPUTED_VALUE"""),3000000.0) -> 3000000 | L94: =IFERROR(__xludf.DUMMYFUNCTION("""COMPUTED_VALUE"""),3000000.0) -> 3000000 | M94: 45945 | N94: BCA MPG | O94: 3000000 | P94: 45945 | R94: =L94-O94 -> 0
B95: =IFERROR(__xludf.DUMMYFUNCTION("""COMPUTED_VALUE"""),"PT. Top Point") -> PT. Top Point | C95: =IFERROR(__xludf.DUMMYFUNCTION("""COMPUTED_VALUE"""),"Pemesanan PO Ke 8 (RSPP)") -> Pemesanan PO Ke 8 (RSPP) | E95: =IFERROR(__xludf.DUMMYFUNCTION("""COMPUTED_VALUE"""),"sp rspp (po 8)") -> sp rspp (po 8) | F95: =IFERROR(__xludf.DUMMYFUNCTION("""COMPUTED_VALUE"""),"MPG-131025011 - Top Point (RSPP).pdf") -> MPG-131025011 - Top Point (RSPP).pdf | G95: =IFERROR(__xludf.DUMMYFUNCTION("""COMPUTED_VALUE"""),45940.0) -> 45940 | H95: =IFERROR(__xludf.DUMMYFUNCTION("""COMPUTED_VALUE"""),"tempo") -> tempo | I95: =IFERROR(__xludf.DUMMYFUNCTION("""COMPUTED_VALUE"""),4560810.81081081) -> 4560810.8 | J95: =IFERROR(__xludf.DUMMYFUNCTION("""COMPUTED_VALUE"""),501689.1891891891) -> 501689.19 | L95: =IFERROR(__xludf.DUMMYFUNCTION("""COMPUTED_VALUE"""),5062500.0) -> 5062500 | M95: 45973 | N95: BCA MPG | O95: =L95 -> 5062500 | P95: 45973 | R95: =L95-O95 -> 0 | S95: - | U95: ?
B96: =IFERROR(__xludf.DUMMYFUNCTION("""COMPUTED_VALUE"""),"PT. Top Point") -> PT. Top Point | C96: =IFERROR(__xludf.DUMMYFUNCTION("""COMPUTED_VALUE"""),"Stock suntikan rspp") -> Stock suntikan rspp | E96: =IFERROR(__xludf.DUMMYFUNCTION("""COMPUTED_VALUE"""),"RSPP - (PO KE 9)") -> RSPP - (PO KE 9) | F96: =IFERROR(__xludf.DUMMYFUNCTION("""COMPUTED_VALUE"""),"MPG-141025019 - Top Point (Stock RSPP).pdf") -> MPG-141025019 - Top Point (Stock RSPP).pdf | G96: =IFERROR(__xludf.DUMMYFUNCTION("""COMPUTED_VALUE"""),45946.0) -> 45946 | H96: =IFERROR(__xludf.DUMMYFUNCTION("""COMPUTED_VALUE"""),"tempo") -> tempo | I96: =IFERROR(__xludf.DUMMYFUNCTION("""COMPUTED_VALUE"""),6081081.0) -> 6081081 | J96: =IFERROR(__xludf.DUMMYFUNCTION("""COMPUTED_VALUE"""),668919.0) -> 668919 | L96: =IFERROR(__xludf.DUMMYFUNCTION("""COMPUTED_VALUE"""),6750000.0) -> 6750000 | M96: 45986 | N96: BCA MPG | O96: =L96 -> 6750000 | P96: 45986 | R96: =L96-O96 -> 0 | S96: -
C97: =IFERROR(__xludf.DUMMYFUNCTION("""COMPUTED_VALUE"""),"Lalamove antar barang pesanan rs adjidarmo") -> Lalamove antar barang pesanan rs adjidarmo | G97: =IFERROR(__xludf.DUMMYFUNCTION("""COMPUTED_VALUE"""),45946.0) -> 45946 | I97: =IFERROR(__xludf.DUMMYFUNCTION("""COMPUTED_VALUE"""),300000.0) -> 300000 | L97: =IFERROR(__xludf.DUMMYFUNCTION("""COMPUTED_VALUE"""),300000.0) -> 300000 | M97: 45946 | N97: BCA MPG | O97: 300000 | P97: 45946 | R97: =L97-O97 -> 0
C98: =IFERROR(__xludf.DUMMYFUNCTION("""COMPUTED_VALUE"""),"Advance rizky bertemu kepala pkm pasir angin") -> Advance rizky bertemu kepala pkm pasir angin | G98: =IFERROR(__xludf.DUMMYFUNCTION("""COMPUTED_VALUE"""),45946.0) -> 45946 | I98: =IFERROR(__xludf.DUMMYFUNCTION("""COMPUTED_VALUE"""),500000.0) -> 500000 | L98: =IFERROR(__xludf.DUMMYFUNCTION("""COMPUTED_VALUE"""),500000.0) -> 500000 | M98: 45946 | N98: BCA MPG | O98: 500000 | P98: 45946 | R98: =L98-O98 -> 0
C99: =IFERROR(__xludf.DUMMYFUNCTION("""COMPUTED_VALUE"""),"Pembelian pesanan (UPK KEMENKES)") -> Pembelian pesanan (UPK KEMENKES) | E99: =IFERROR(__xludf.DUMMYFUNCTION("""COMPUTED_VALUE"""),"surat-pesanan-EP-01K7DPKYXJ1AF4X8HQ0MZ3N8DV UPK KEMENKES.pdf") -> surat-pesanan-EP-01K7DPKYXJ1AF4X8HQ0MZ3N8DV UPK KEMENKES.pdf | G99: =IFERROR(__xludf.DUMMYFUNCTION("""COMPUTED_VALUE"""),45947.0) -> 45947 | I99: =IFERROR(__xludf.DUMMYFUNCTION("""COMPUTED_VALUE"""),328500.0) -> 328500 | L99: =IFERROR(__xludf.DUMMYFUNCTION("""COMPUTED_VALUE"""),328500.0) -> 328500 | M99: 45947 | N99: BCA MPG | O99: 328500 | P99: 45947 | R99: =L99-O99 -> 0
B100: =IFERROR(__xludf.DUMMYFUNCTION("""COMPUTED_VALUE"""),"PT. MBC") -> PT. MBC | C100: =IFERROR(__xludf.DUMMYFUNCTION("""COMPUTED_VALUE"""),"Pembelian ganti barang rusak (pkm balekambang)") -> Pembelian ganti barang rusak (pkm balekambang) | E100: =IFERROR(__xludf.DUMMYFUNCTION("""COMPUTED_VALUE"""),"Pesanan Balekambang ") -> Pesanan Balekambang | I100: =IFERROR(__xludf.DUMMYFUNCTION("""COMPUTED_VALUE"""),536250.0) -> 536250 | J100: =IFERROR(__xludf.DUMMYFUNCTION("""COMPUTED_VALUE"""),58988.0) -> 58988 | L100: =IFERROR(__xludf.DUMMYFUNCTION("""COMPUTED_VALUE"""),595238.0) -> 595238 | M100: 45947 | N100: BCA MPG | O100: 595238 | P100: 45947 | R100: =L100-O100 -> 0
...

Sheet Sheet3
G6: Pemerintah | H6: Pemungut
D9: laptop | E9: 1000000
D10: mouse | E10: 500000
D11: Total | E11: =E9+E10 -> 1500000
D13: DPP | E13: =E11/1.11 -> 1351351.4 | F13: ini setara nilai invoice
D14: PPN | E14: =E13*11% -> 148648.65 | F14: 0.11 | G14: 0.12
D15: PPH | E15: =E13*1.5% -> 20270.27 | F15: 0.015
D16: NET RECEIPT | E16: =E13-E14-E15 -> 1182432.4
D18: DPP LAIINYA | E18: =E13*11/12 -> 1238738.7
D19: PPN | E19: =E18*12% -> 148648.65

Sheet JE
A2: AC No. | B2: Account Name | C2: Dr. | D2: Cr.
B3: Purchases Journal
A4: 50100-00 | B4: Pembelian | C4: =PURCHASES!L377 -> 1476737831
A5: 22104-00 | B5: Hutang PPh 23 | D5: =PURCHASES!K380
A6: 11411 | B6: Value added tax-input | C6: =PURCHASES!J380
A7: 21111 | B7: Trade payables-Rp | D7: =SUM(C4:C7)-SUM(D4:D6) -> 1476737831
H16: Pada saat beli
I18: Pembelian | K18: 10
J19: hutang | L19: 10
C23: =SUM(C4:C22) -> 1476737831 | D23: =SUM(D4:D22) -> 1476737831 | I23: Hutang | K23: 10
J24: BCA | L24: 10

Sheet Margin
